Workbook

Sheet Mês a Mês
A1: Entradas | B1: Previstas | C1: Efetivadas | E1: Mês | F1: A pagar | G1: Previsão | H1: Pago | I1: Falta
A2: Salário | B2: 7297.86 | C2: 7297.86 | E2: =IFERROR(__xludf.DUMMYFUNCTION("QUERY(UNIQUE(FILTER(Controle!F2:F1000,Controle!F2:F1000<>"""",Controle!E2:E1000>=DATE(YEAR(EDATE(TODAY(),-1)),MONTH(EDATE(TODAY(),-1)),""01""))),""LIMIT 12"")"),"7/2026") -> 7/2026 | F2: =SUMIFS(Controle!G:G,Controle!F:F,CONCAT("=",$E2),Controle!H:H,"=0") -> 0 | G2: =$B$10-$F2 -> 8297.86 | H2: =SUMIFS(Controle!H:H,Controle!F:F,CONCAT("=",$E2),Controle!I:I,"<>") -> 13020.34 | I2: =IF(F2>H2,F2-H2,0) -> 0
A3: Comissão tia Noeli | B3: 1000 | C3: 210 | E3: =IFERROR(__xludf.DUMMYFUNCTION("""COMPUTED_VALUE"""),"8/2026") -> 8/2026 | F3: =SUMIFS(Controle!G:G,Controle!F:F,CONCAT("=",$E3),Controle!H:H,"=0") -> 0 | G3: =$B$10-$F3 -> 8297.86 | H3: =SUMIFS(Controle!H:H,Controle!F:F,CONCAT("=",$E3),Controle!I:I,"<>") -> 10578.62 | I3: =IF(F3>H3,F3-H3,0) -> 0
E4: =IFERROR(__xludf.DUMMYFUNCTION("""COMPUTED_VALUE"""),"9/2026") -> 9/2026 | F4: =SUMIFS(Controle!G:G,Controle!F:F,CONCAT("=",$E4),Controle!H:H,"=0") -> 9373.86 | G4: =$B$10-$F4 -> -1076 | H4: =SUMIFS(Controle!H:H,Controle!F:F,CONCAT("=",$E4),Controle!I:I,"<>") -> 3401.62 | I4: =IF(F4>H4,F4-H4,0) -> 5972.24
E5: =IFERROR(__xludf.DUMMYFUNCTION("""COMPUTED_VALUE"""),"10/2026") -> 10/2026 | F5: =SUMIFS(Controle!G:G,Controle!F:F,CONCAT("=",$E5),Controle!H:H,"=0") -> 4652.76 | G5: =$B$10-$F5 -> 3645.1 | H5: =SUMIFS(Controle!H:H,Controle!F:F,CONCAT("=",$E5),Controle!I:I,"<>") -> 3401.62 | I5: =IF(F5>H5,F5-H5,0) -> 1251.14
E6: =IFERROR(__xludf.DUMMYFUNCTION("""COMPUTED_VALUE"""),"11/2026") -> 11/2026 | F6: =SUMIFS(Controle!G:G,Controle!F:F,CONCAT("=",$E6),Controle!H:H,"=0") -> 5627.76 | G6: =$B$10-$F6 -> 2670.1 | H6: =SUMIFS(Controle!H:H,Controle!F:F,CONCAT("=",$E6),Controle!I:I,"<>") -> 901.22 | I6: =IF(F6>H6,F6-H6,0) -> 4726.54
E7: =IFERROR(__xludf.DUMMYFUNCTION("""COMPUTED_VALUE"""),"12/2026") -> 12/2026 | F7: =SUMIFS(Controle!G:G,Controle!F:F,CONCAT("=",$E7),Controle!H:H,"=0") -> 24812.58 | G7: =$B$10-$F7 -> -16514.72 | H7: =SUMIFS(Controle!H:H,Controle!F:F,CONCAT("=",$E7),Controle!I:I,"<>") -> 901.22 | I7: =IF(F7>H7,F7-H7,0) -> 23911.36
E8: =IFERROR(__xludf.DUMMYFUNCTION("""COMPUTED_VALUE"""),"1/2027") -> 1/2027 | F8: =SUMIFS(Controle!G:G,Controle!F:F,CONCAT("=",$E8),Controle!H:H,"=0") -> 4219.71 | G8: =$B$10-$F8 -> 4078.15 | H8: =SUMIFS(Controle!H:H,Controle!F:F,CONCAT("=",$E8),Controle!I:I,"<>") -> 901.22 | I8: =IF(F8>H8,F8-H8,0) -> 3318.49
E9: =IFERROR(__xludf.DUMMYFUNCTION("""COMPUTED_VALUE"""),"2/2027") -> 2/2027 | F9: =SUMIFS(Controle!G:G,Controle!F:F,CONCAT("=",$E9),Controle!H:H,"=0") -> 4219.71 | G9: =$B$10-$F9 -> 4078.15 | H9: =SUMIFS(Controle!H:H,Controle!F:F,CONCAT("=",$E9),Controle!I:I,"<>") -> 901.22 | I9: =IF(F9>H9,F9-H9,0) -> 3318.49
A10: Total | B10: =SUM(B2:B9) -> 8297.86 | C10: =SUM(C2:C9) -> 7507.86 | E10: =IFERROR(__xludf.DUMMYFUNCTION("""COMPUTED_VALUE"""),"3/2027") -> 3/2027 | F10: =SUMIFS(Controle!G:G,Controle!F:F,CONCAT("=",$E10),Controle!H:H,"=0") -> 4219.71 | G10: =$B$10-$F10 -> 4078.15 | H10: =SUMIFS(Controle!H:H,Controle!F:F,CONCAT("=",$E10),Controle!I:I,"<>") -> 901.22 | I10: =IF(F10>H10,F10-H10,0) -> 3318.49
E11: =IFERROR(__xludf.DUMMYFUNCTION("""COMPUTED_VALUE"""),"4/2027") -> 4/2027 | F11: =SUMIFS(Controle!G:G,Controle!F:F,CONCAT("=",$E11),Controle!H:H,"=0") -> 4219.71 | G11: =$B$10-$F11 -> 4078.15 | H11: =SUMIFS(Controle!H:H,Controle!F:F,CONCAT("=",$E11),Controle!I:I,"<>") -> 901.22 | I11: =IF(F11>H11,F11-H11,0) -> 3318.49
E12: =IFERROR(__xludf.DUMMYFUNCTION("""COMPUTED_VALUE"""),"5/2027") -> 5/2027 | F12: =SUMIFS(Controle!G:G,Controle!F:F,CONCAT("=",$E12),Controle!H:H,"=0") -> 4219.71 | G12: =$B$10-$F12 -> 4078.15 | H12: =SUMIFS(Controle!H:H,Controle!F:F,CONCAT("=",$E12),Controle!I:I,"<>") -> 901.22 | I12: =IF(F12>H12,F12-H12,0) -> 3318.49
E13: =IFERROR(__xludf.DUMMYFUNCTION("""COMPUTED_VALUE"""),"6/2027") -> 6/2027 | F13: =SUMIFS(Controle!G:G,Controle!F:F,CONCAT("=",$E13),Controle!H:H,"=0") -> 4219.71 | G13: =$B$10-$F13 -> 4078.15 | H13: =SUMIFS(Controle!H:H,Controle!F:F,CONCAT("=",$E13),Controle!I:I,"<>") -> 901.22 | I13: =IF(F13>H13,F13-H13,0) -> 3318.49
A16: 7000 | B16: 7073.23 | C16: =B16-A16 -> 73.23
A17: 2000000 | B17: =(A17*B16)/A16 -> 2020922.9 | C17: =B17-A17 -> 20922.857
B21: =B17/A17 -> 1.0104614 | C21: =B17*B21 -> 2042064.6 | D21: =C21-B17 -> 21141.74

Sheet Dashboard
A1: Mês | B1: 9/2026 | E1: Vencimento | F1: Link | G1: Contas | H1: Pago | I1: Á Pagar | J1: Total | L1: Mês | M1: A pagar | N1: Pago | O1: Falta | Q1: Credor | R1: Pago | S1: Devendo | T1: Total | V1: Fornecedor | W1: Pago | X1: Devendo | Y1: Total | AA1: Destino | AB1: Pago | AD1: Categorias | AE1: Pago
A2: Pago | B2: =SUMIFS(Controle!H:H,Controle!F:F,CONCAT("=",$B$1),Controle!I:I,"<>") -> 3401.62 | E2: =IFERROR(__xludf.DUMMYFUNCTION("SORT(UNIQUE(FILTER(Controle!E:E,Controle!F:F=$B$1)))"),46269.0) -> 46269 | F2: =HYPERLINK("https://docs.google.com/spreadsheets/d/1Uj96w5r3n0cneD7LaJDh3hKPtO69t6MtHFm4lkQ5K7I/edit?gid=775169775#gid=775169775&range=A"&MATCH(E2,Controle!E:E,0),"Ir") -> Ir | G2: =COUNTIF(Controle!E:E,CONCAT("=",E2)) -> 1 | H2: =SUMIFS(Controle!G:G,Controle!E:E,CONCAT("=",$E2),Controle!H:H,"<>0") -> 0 | I2: =SUMIFS(Controle!G:G,Controle!E:E,CONCAT("=",$E2),Controle!H:H,"=0") -> 1236.78 | J2: =SUMIFS(Controle!G:G,Controle!E:E,CONCAT("=",$E2)) -> 1236.78 | L2: =IFERROR(__xludf.DUMMYFUNCTION("QUERY(UNIQUE(FILTER(Controle!F2:F1009,Controle!F2:F1009<>"""",Controle!E2:E1009>=DATE(YEAR(EDATE(TODAY(),-1)),MONTH(EDATE(TODAY(),-1)),""01""))),""LIMIT 12"")"),"7/2026") -> 7/2026 | M2: =SUMIFS(Controle!G:G,Controle!F:F,CONCAT("=",$L2),Controle!H:H,"=0") -> 0 | N2: =SUMIFS(Controle!H:H,Controle!F:F,CONCAT("=",$L2),Controle!I:I,"<>") -> 13020.34 | O2: =IF(M2>N2,M2-N2,0) -> 0 | Q2: =IFERROR(__xludf.DUMMYFUNCTION("SORT(UNIQUE(FILTER(Controle!A:A,Controle!C:C=""Dívida"")))"),"Ademicon") -> Ademicon | R2: =SUMIFS(Controle!G:G,Controle!A:A,CONCAT("=",$Q2),Controle!H:H,"<>0") -> 44652 | S2: =SUMIFS(Controle!G:G,Controle!A:A,CONCAT("=",$Q2),Controle!H:H,"=0") -> 95810.05 | T2: =SUMIFS(Controle!G:G,Controle!A:A,CONCAT("=",$Q2)) -> 140462.05 | V2: =IFERROR(__xludf.DUMMYFUNCTION("UNIQUE(FILTER(Controle!A:A,Controle!C:C=""Fornecedor""))"),"Élio Squena - Tordilho Negro") -> Élio Squena - Tordilho Negro | W2: =SUMIFS(Controle!G:G,Controle!A:A,CONCAT("=",$V2),Controle!H:H,"<>0") -> 1717.87 | X2: =SUMIFS(Controle!G:G,Controle!A:A,CONCAT("=",$V2),Controle!H:H,"=0") -> 19976.48 | Y2: =SUMIFS(Controle!G:G,Controle!A:A,CONCAT("=",$V2)) -> 21694.35 | AA2: =IFERROR(__xludf.DUMMYFUNCTION("UNIQUE(FILTER(Controle!A2:A1009,Controle!C2:C1009<>""Fornecedor"",Controle!C2:C1009<>""Dívida""))"),"Copel") -> Copel | AB2: =SUMIFS(Controle!H:H,Controle!A:A,CONCAT("=",$AA2),Controle!I:I,"<>0") -> 7988.43 | AD2: {=SORT(UNIQUE(Categorias!A:A))} -> Água | AE2: =SUMIFS(Controle!H:H,Controle!D:D,CONCAT("=",$AD2),Controle!I:I,"<>0") -> 3835.4
A3: À Pagar | B3: =SUMIFS(Controle!G:G,Controle!F:F,CONCAT("=",$B$1),Controle!I:I,"=") -> 9373.86 | E3: =IFERROR(__xludf.DUMMYFUNCTION("""COMPUTED_VALUE"""),46272.0) -> 46272 | F3: =HYPERLINK("https://docs.google.com/spreadsheets/d/1Uj96w5r3n0cneD7LaJDh3hKPtO69t6MtHFm4lkQ5K7I/edit?gid=775169775#gid=775169775&range=A"&MATCH(E3,Controle!E:E,0),"Ir") -> Ir | G3: =COUNTIF(Controle!E:E,CONCAT("=",E3)) -> 1 | H3: =SUMIFS(Controle!G:G,Controle!E:E,CONCAT("=",$E3),Controle!H:H,"<>0") -> 1231.13 | I3: =SUMIFS(Controle!G:G,Controle!E:E,CONCAT("=",$E3),Controle!H:H,"=0") -> 0 | J3: =SUMIFS(Controle!G:G,Controle!E:E,CONCAT("=",$E3)) -> 1231.13 | L3: =IFERROR(__xludf.DUMMYFUNCTION("""COMPUTED_VALUE"""),"8/2026") -> 8/2026 | M3: =SUMIFS(Controle!G:G,Controle!F:F,CONCAT("=",$L3),Controle!H:H,"=0") -> 0 | N3: =SUMIFS(Controle!H:H,Controle!F:F,CONCAT("=",$L3),Controle!I:I,"<>") -> 10578.62 | O3: =IF(M3>N3,M3-N3,0) -> 0 | Q3: =IFERROR(__xludf.DUMMYFUNCTION("""COMPUTED_VALUE"""),"CC Cresol") -> CC Cresol | R3: =SUMIFS(Controle!G:G,Controle!A:A,CONCAT("=",$Q3),Controle!H:H,"<>0") -> 7469.5 | S3: =SUMIFS(Controle!G:G,Controle!A:A,CONCAT("=",$Q3),Controle!H:H,"=0") -> 0 | T3: =SUMIFS(Controle!G:G,Controle!A:A,CONCAT("=",$Q3)) -> 7469.5 | V3: =IFERROR(__xludf.DUMMYFUNCTION("""COMPUTED_VALUE"""),"Pampasul") -> Pampasul | W3: =SUMIFS(Controle!G:G,Controle!A:A,CONCAT("=",$V3),Controle!H:H,"<>0") -> 9005.58 | X3: =SUMIFS(Controle!G:G,Controle!A:A,CONCAT("=",$V3),Controle!H:H,"=0") -> 0 | Y3: =SUMIFS(Controle!G:G,Controle!A:A,CONCAT("=",$V3)) -> 9005.58 | AA3: =IFERROR(__xludf.DUMMYFUNCTION("""COMPUTED_VALUE"""),"Sanepar") -> Sanepar | AB3: =SUMIFS(Controle!H:H,Controle!A:A,CONCAT("=",$AA3),Controle!I:I,"<>0") -> 3835.4 | AD3: Categorias de conta | AE3: =SUMIFS(Controle!H:H,Controle!D:D,CONCAT("=",$AD3),Controle!I:I,"<>0") -> 0
A4: Vence hoje | B4: =SUMIFS(Controle!G:G,Controle!E:E,CONCATENATE("<=",DAY(NOW()),"/",MONTH(NOW()),"/",YEAR(NOW())),Controle!I:I,"=") -> 0 | E4: =IFERROR(__xludf.DUMMYFUNCTION("""COMPUTED_VALUE"""),46273.0) -> 46273 | F4: =HYPERLINK("https://docs.google.com/spreadsheets/d/1Uj96w5r3n0cneD7LaJDh3hKPtO69t6MtHFm4lkQ5K7I/edit?gid=775169775#gid=775169775&range=A"&MATCH(E4,Controle!E:E,0),"Ir") -> Ir | G4: =COUNTIF(Controle!E:E,CONCAT("=",E4)) -> 5 | H4: =SUMIFS(Controle!G:G,Controle!E:E,CONCAT("=",$E4),Controle!H:H,"<>0") -> 0 | I4: =SUMIFS(Controle!G:G,Controle!E:E,CONCAT("=",$E4),Controle!H:H,"=0") -> 7633.5 | J4: =SUMIFS(Controle!G:G,Controle!E:E,CONCAT("=",$E4)) -> 7633.5 | L4: =IFERROR(__xludf.DUMMYFUNCTION("""COMPUTED_VALUE"""),"9/2026") -> 9/2026 | M4: =SUMIFS(Controle!G:G,Controle!F:F,CONCAT("=",$L4),Controle!H:H,"=0") -> 9373.86 | N4: =SUMIFS(Controle!H:H,Controle!F:F,CONCAT("=",$L4),Controle!I:I,"<>") -> 3401.62 | O4: =IF(M4>N4,M4-N4,0) -> 5972.24 | Q4: =IFERROR(__xludf.DUMMYFUNCTION("""COMPUTED_VALUE"""),"CC Itaú") -> CC Itaú | R4: =SUMIFS(Controle!G:G,Controle!A:A,CONCAT("=",$Q4),Controle!H:H,"<>0") -> 25573.85 | S4: =SUMIFS(Controle!G:G,Controle!A:A,CONCAT("=",$Q4),Controle!H:H,"=0") -> 1068.8 | T4: =SUMIFS(Controle!G:G,Controle!A:A,CONCAT("=",$Q4)) -> 26642.65 | V4: =IFERROR(__xludf.DUMMYFUNCTION("""COMPUTED_VALUE"""),"Botinas") -> Botinas | W4: =SUMIFS(Controle!G:G,Controle!A:A,CONCAT("=",$V4),Controle!H:H,"<>0") -> 2000 | X4: =SUMIFS(Controle!G:G,Controle!A:A,CONCAT("=",$V4),Controle!H:H,"=0") -> 0 | Y4: =SUMIFS(Controle!G:G,Controle!A:A,CONCAT("=",$V4)) -> 2000 | AA4: =IFERROR(__xludf.DUMMYFUNCTION("""COMPUTED_VALUE"""),"Aluguel") -> Aluguel | AB4: =SUMIFS(Controle!H:H,Controle!A:A,CONCAT("=",$AA4),Controle!I:I,"<>0") -> 24022.6 | AD4: Combustivel | AE4: =SUMIFS(Controle!H:H,Controle!D:D,CONCAT("=",$AD4),Controle!I:I,"<>0") -> 100
E5: =IFERROR(__xludf.DUMMYFUNCTION("""COMPUTED_VALUE"""),46275.0) -> 46275 | F5: =HYPERLINK("https://docs.google.com/spreadsheets/d/1Uj96w5r3n0cneD7LaJDh3hKPtO69t6MtHFm4lkQ5K7I/edit?gid=775169775#gid=775169775&range=A"&MATCH(E5,Controle!E:E,0),"Ir") -> Ir | G5: =COUNTIF(Controle!E:E,CONCAT("=",E5)) -> 2 | H5: =SUMIFS(Controle!G:G,Controle!E:E,CONCAT("=",$E5),Controle!H:H,"<>0") -> 0 | I5: =SUMIFS(Controle!G:G,Controle!E:E,CONCAT("=",$E5),Controle!H:H,"=0") -> 334.48 | J5: =SUMIFS(Controle!G:G,Controle!E:E,CONCAT("=",$E5)) -> 334.48 | L5: =IFERROR(__xludf.DUMMYFUNCTION("""COMPUTED_VALUE"""),"10/2026") -> 10/2026 | M5: =SUMIFS(Controle!G:G,Controle!F:F,CONCAT("=",$L5),Controle!H:H,"=0") -> 4652.76 | N5: =SUMIFS(Controle!H:H,Controle!F:F,CONCAT("=",$L5),Controle!I:I,"<>") -> 3401.62 | O5: =IF(M5>N5,M5-N5,0) -> 1251.14 | Q5: =IFERROR(__xludf.DUMMYFUNCTION("""COMPUTED_VALUE"""),"CC Nubank") -> CC Nubank | R5: =SUMIFS(Controle!G:G,Controle!A:A,CONCAT("=",$Q5),Controle!H:H,"<>0") -> 48008.41 | S5: =SUMIFS(Controle!G:G,Controle!A:A,CONCAT("=",$Q5),Controle!H:H,"=0") -> 417.28 | T5: =SUMIFS(Controle!G:G,Controle!A:A,CONCAT("=",$Q5)) -> 48425.69 | V5: =IFERROR(__xludf.DUMMYFUNCTION("""COMPUTED_VALUE"""),"Qualitchê") -> Qualitchê | W5: =SUMIFS(Controle!G:G,Controle!A:A,CONCAT("=",$V5),Controle!H:H,"<>0") -> 2643.2 | X5: =SUMIFS(Controle!G:G,Controle!A:A,CONCAT("=",$V5),Controle!H:H,"=0") -> 0 | Y5: =SUMIFS(Controle!G:G,Controle!A:A,CONCAT("=",$V5)) -> 2643.2 | AA5: =IFERROR(__xludf.DUMMYFUNCTION("""COMPUTED_VALUE"""),"TIM") -> TIM | AB5: =SUMIFS(Controle!H:H,Controle!A:A,CONCAT("=",$AA5),Controle!I:I,"<>0") -> 1297.88 | AD5: Dívida | AE5: =SUMIFS(Controle!H:H,Controle!D:D,CONCAT("=",$AD5),Controle!I:I,"<>0") -> 145445.38
E6: =IFERROR(__xludf.DUMMYFUNCTION("""COMPUTED_VALUE"""),46285.0) -> 46285 | F6: =HYPERLINK("https://docs.google.com/spreadsheets/d/1Uj96w5r3n0cneD7LaJDh3hKPtO69t6MtHFm4lkQ5K7I/edit?gid=775169775#gid=775169775&range=A"&MATCH(E6,Controle!E:E,0),"Ir") -> Ir | G6: =COUNTIF(Controle!E:E,CONCAT("=",E6)) -> 2 | H6: =SUMIFS(Controle!G:G,Controle!E:E,CONCAT("=",$E6),Controle!H:H,"<>0") -> 0 | I6: =SUMIFS(Controle!G:G,Controle!E:E,CONCAT("=",$E6),Controle!H:H,"=0") -> 169.1 | J6: =SUMIFS(Controle!G:G,Controle!E:E,CONCAT("=",$E6)) -> 169.1 | L6: =IFERROR(__xludf.DUMMYFUNCTION("""COMPUTED_VALUE"""),"11/2026") -> 11/2026 | M6: =SUMIFS(Controle!G:G,Controle!F:F,CONCAT("=",$L6),Controle!H:H,"=0") -> 5627.76 | N6: =SUMIFS(Controle!H:H,Controle!F:F,CONCAT("=",$L6),Controle!I:I,"<>") -> 901.22 | O6: =IF(M6>N6,M6-N6,0) -> 4726.54 | Q6: =IFERROR(__xludf.DUMMYFUNCTION("""COMPUTED_VALUE"""),"CC Santander") -> CC Santander | R6: =SUMIFS(Controle!G:G,Controle!A:A,CONCAT("=",$Q6),Controle!H:H,"<>0") -> 227332.8 | S6: =SUMIFS(Controle!G:G,Controle!A:A,CONCAT("=",$Q6),Controle!H:H,"=0") -> 8384.95 | T6: =SUMIFS(Controle!G:G,Controle!A:A,CONCAT("=",$Q6)) -> 235717.75 | V6: =IFERROR(__xludf.DUMMYFUNCTION("""COMPUTED_VALUE"""),"Sokolowski") -> Sokolowski | W6: =SUMIFS(Controle!G:G,Controle!A:A,CONCAT("=",$V6),Controle!H:H,"<>0") -> 207.27 | X6: =SUMIFS(Controle!G:G,Controle!A:A,CONCAT("=",$V6),Controle!H:H,"=0") -> 0 | Y6: =SUMIFS(Controle!G:G,Controle!A:A,CONCAT("=",$V6)) -> 207.27 | AA6: =IFERROR(__xludf.DUMMYFUNCTION("""COMPUTED_VALUE"""),"Meganet") -> Meganet | AB6: =SUMIFS(Controle!H:H,Controle!A:A,CONCAT("=",$AA6),Controle!I:I,"<>0") -> 5994.9 | AD6: Imposto | AE6: =SUMIFS(Controle!H:H,Controle!D:D,CONCAT("=",$AD6),Controle!I:I,"<>0") -> 4125.9
A7: Local | B7: Valor | C7: Aplicação | E7: =IFERROR(__xludf.DUMMYFUNCTION("""COMPUTED_VALUE"""),46291.0) -> 46291 | F7: =HYPERLINK("https://docs.google.com/spreadsheets/d/1Uj96w5r3n0cneD7LaJDh3hKPtO69t6MtHFm4lkQ5K7I/edit?gid=775169775#gid=775169775&range=A"&MATCH(E7,Controle!E:E,0),"Ir") -> Ir | G7: =COUNTIF(Controle!E:E,CONCAT("=",E7)) -> 1 | H7: =SUMIFS(Controle!G:G,Controle!E:E,CONCAT("=",$E7),Controle!H:H,"<>0") -> 2500.4 | I7: =SUMIFS(Controle!G:G,Controle!E:E,CONCAT("=",$E7),Controle!H:H,"=0") -> 0 | J7: =SUMIFS(Controle!G:G,Controle!E:E,CONCAT("=",$E7)) -> 2500.4 | L7: =IFERROR(__xludf.DUMMYFUNCTION("""COMPUTED_VALUE"""),"12/2026") -> 12/2026 | M7: =SUMIFS(Controle!G:G,Controle!F:F,CONCAT("=",$L7),Controle!H:H,"=0") -> 24812.58 | N7: =SUMIFS(Controle!H:H,Controle!F:F,CONCAT("=",$L7),Controle!I:I,"<>") -> 901.22 | O7: =IF(M7>N7,M7-N7,0) -> 23911.36 | Q7: =IFERROR(__xludf.DUMMYFUNCTION("""COMPUTED_VALUE"""),"Empréstimo Consignado") -> Empréstimo Consignado | R7: =SUMIFS(Controle!G:G,Controle!A:A,CONCAT("=",$Q7),Controle!H:H,"<>0") -> 20003.2 | S7: =SUMIFS(Controle!G:G,Controle!A:A,CONCAT("=",$Q7),Controle!H:H,"=0") -> 160025.6 | T7: =SUMIFS(Controle!G:G,Controle!A:A,CONCAT("=",$Q7)) -> 180028.8 | V7: =IFERROR(__xludf.DUMMYFUNCTION("""COMPUTED_VALUE"""),"Ciarin") -> Ciarin | W7: =SUMIFS(Controle!G:G,Controle!A:A,CONCAT("=",$V7),Controle!H:H,"<>0") -> 551.08 | X7: =SUMIFS(Controle!G:G,Controle!A:A,CONCAT("=",$V7),Controle!H:H,"=0") -> 0 | Y7: =SUMIFS(Controle!G:G,Controle!A:A,CONCAT("=",$V7)) -> 551.08 | AA7: =IFERROR(__xludf.DUMMYFUNCTION("""COMPUTED_VALUE"""),"MEI") -> MEI | AB7: =SUMIFS(Controle!H:H,Controle!A:A,CONCAT("=",$AA7),Controle!I:I,"<>0") -> 4125.9 | AD7: Internet | AE7: =SUMIFS(Controle!H:H,Controle!D:D,CONCAT("=",$AD7),Controle!I:I,"<>0") -> 5994.9
A8: Santander | B8: =273.77+1005 -> 1278.77 | C8: 1385.73 | F8: =HYPERLINK("https://docs.google.com/spreadsheets/d/1Uj96w5r3n0cneD7LaJDh3hKPtO69t6MtHFm4lkQ5K7I/edit?gid=775169775#gid=775169775&range=A"&MATCH(E8,Controle!E:E,0),"Ir") -> #N/A | G8: =COUNTIF(Controle!E:E,CONCAT("=",E8)) -> 1214 | H8: =SUMIFS(Controle!G:G,Controle!E:E,CONCAT("=",$E8),Controle!H:H,"<>0") -> 0 | I8: =SUMIFS(Controle!G:G,Controle!E:E,CONCAT("=",$E8),Controle!H:H,"=0") -> 0 | J8: =SUMIFS(Controle!G:G,Controle!E:E,CONCAT("=",$E8)) -> 0 | L8: =IFERROR(__xludf.DUMMYFUNCTION("""COMPUTED_VALUE"""),"1/2027") -> 1/2027 | M8: =SUMIFS(Controle!G:G,Controle!F:F,CONCAT("=",$L8),Controle!H:H,"=0") -> 4219.71 | N8: =SUMIFS(Controle!H:H,Controle!F:F,CONCAT("=",$L8),Controle!I:I,"<>") -> 901.22 | O8: =IF(M8>N8,M8-N8,0) -> 3318.49 | Q8: =IFERROR(__xludf.DUMMYFUNCTION("""COMPUTED_VALUE"""),"Empréstimo Cresol") -> Empréstimo Cresol | R8: =SUMIFS(Controle!G:G,Controle!A:A,CONCAT("=",$Q8),Controle!H:H,"<>0") -> 24376.02 | S8: =SUMIFS(Controle!G:G,Controle!A:A,CONCAT("=",$Q8),Controle!H:H,"=0") -> 0 | T8: =SUMIFS(Controle!G:G,Controle!A:A,CONCAT("=",$Q8)) -> 24376.02 | V8: =IFERROR(__xludf.DUMMYFUNCTION("""COMPUTED_VALUE"""),"MOR") -> MOR | W8: =SUMIFS(Controle!G:G,Controle!A:A,CONCAT("=",$V8),Controle!H:H,"<>0") -> 1348.33 | X8: =SUMIFS(Controle!G:G,Controle!A:A,CONCAT("=",$V8),Controle!H:H,"=0") -> 0 | Y8: =SUMIFS(Controle!G:G,Controle!A:A,CONCAT("=",$V8)) -> 1348.33 | AA8: =IFERROR(__xludf.DUMMYFUNCTION("""COMPUTED_VALUE"""),"Seguro Kwid") -> Seguro Kwid | AB8: =SUMIFS(Controle!H:H,Controle!A:A,CONCAT("=",$AA8),Controle!I:I,"<>0") -> 1715.8 | AD8: Investimento | AE8: =SUMIFS(Controle!H:H,Controle!D:D,CONCAT("=",$AD8),Controle!I:I,"<>0") -> 368231.99
A9: Cresol | B9: =0 -> 0 | F9: =HYPERLINK("https://docs.google.com/spreadsheets/d/1Uj96w5r3n0cneD7LaJDh3hKPtO69t6MtHFm4lkQ5K7I/edit?gid=775169775#gid=775169775&range=A"&MATCH(E9,Controle!E:E,0),"Ir") -> #N/A | G9: =COUNTIF(Controle!E:E,CONCAT("=",E9)) -> 1214 | H9: =SUMIFS(Controle!G:G,Controle!E:E,CONCAT("=",$E9),Controle!H:H,"<>0") -> 0 | I9: =SUMIFS(Controle!G:G,Controle!E:E,CONCAT("=",$E9),Controle!H:H,"=0") -> 0 | J9: =SUMIFS(Controle!G:G,Controle!E:E,CONCAT("=",$E9)) -> 0 | L9: =IFERROR(__xludf.DUMMYFUNCTION("""COMPUTED_VALUE"""),"2/2027") -> 2/2027 | M9: =SUMIFS(Controle!G:G,Controle!F:F,CONCAT("=",$L9),Controle!H:H,"=0") -> 4219.71 | N9: =SUMIFS(Controle!H:H,Controle!F:F,CONCAT("=",$L9),Controle!I:I,"<>") -> 901.22 | O9: =IF(M9>N9,M9-N9,0) -> 3318.49 | Q9: =IFERROR(__xludf.DUMMYFUNCTION("""COMPUTED_VALUE"""),"Empréstimo Nubank") -> Empréstimo Nubank | R9: =SUMIFS(Controle!G:G,Controle!A:A,CONCAT("=",$Q9),Controle!H:H,"<>0") -> 20385.44 | S9: =SUMIFS(Controle!G:G,Controle!A:A,CONCAT("=",$Q9),Controle!H:H,"=0") -> 0 | T9: =SUMIFS(Controle!G:G,Controle!A:A,CONCAT("=",$Q9)) -> 20385.44 | V9: =IFERROR(__xludf.DUMMYFUNCTION("""COMPUTED_VALUE"""),"Black Erva") -> Black Erva | W9: =SUMIFS(Controle!G:G,Controle!A:A,CONCAT("=",$V9),Controle!H:H,"<>0") -> 3681.78 | X9: =SUMIFS(Controle!G:G,Controle!A:A,CONCAT("=",$V9),Controle!H:H,"=0") -> 0 | Y9: =SUMIFS(Controle!G:G,Controle!A:A,CONCAT("=",$V9)) -> 3681.78 | AA9: =IFERROR(__xludf.DUMMYFUNCTION("""COMPUTED_VALUE"""),"NAY Carro de Som") -> NAY Carro de Som | AB9: =SUMIFS(Controle!H:H,Controle!A:A,CONCAT("=",$AA9),Controle!I:I,"<>0") -> 100 | AD9: Locação | AE9: =SUMIFS(Controle!H:H,Controle!D:D,CONCAT("=",$AD9),Controle!I:I,"<>0") -> 24022.6
A10: Infinite Pay | B10: 0 | F10: =HYPERLINK("https://docs.google.com/spreadsheets/d/1Uj96w5r3n0cneD7LaJDh3hKPtO69t6MtHFm4lkQ5K7I/edit?gid=775169775#gid=775169775&range=A"&MATCH(E10,Controle!E:E,0),"Ir") -> #N/A | G10: =COUNTIF(Controle!E:E,CONCAT("=",E10)) -> 1214 | H10: =SUMIFS(Controle!G:G,Controle!E:E,CONCAT("=",$E10),Controle!H:H,"<>0") -> 0 | I10: =SUMIFS(Controle!G:G,Controle!E:E,CONCAT("=",$E10),Controle!H:H,"=0") -> 0 | J10: =SUMIFS(Controle!G:G,Controle!E:E,CONCAT("=",$E10)) -> 0 | L10: =IFERROR(__xludf.DUMMYFUNCTION("""COMPUTED_VALUE"""),"3/2027") -> 3/2027 | M10: =SUMIFS(Controle!G:G,Controle!F:F,CONCAT("=",$L10),Controle!H:H,"=0") -> 4219.71 | N10: =SUMIFS(Controle!H:H,Controle!F:F,CONCAT("=",$L10),Controle!I:I,"<>") -> 901.22 | O10: =IF(M10>N10,M10-N10,0) -> 3318.49 | Q10: =IFERROR(__xludf.DUMMYFUNCTION("""COMPUTED_VALUE"""),"Financiamento Creditas") -> Financiamento Creditas | R10: =SUMIFS(Controle!G:G,Controle!A:A,CONCAT("=",$Q10),Controle!H:H,"<>0") -> 59089.6 | S10: =SUMIFS(Controle!G:G,Controle!A:A,CONCAT("=",$Q10),Controle!H:H,"=0") -> 0 | T10: =SUMIFS(Controle!G:G,Controle!A:A,CONCAT("=",$Q10)) -> 59089.6 | V10: =IFERROR(__xludf.DUMMYFUNCTION("""COMPUTED_VALUE"""),"Mazutti") -> Mazutti | W10: =SUMIFS(Controle!G:G,Controle!A:A,CONCAT("=",$V10),Controle!H:H,"<>0") -> 720 | X10: =SUMIFS(Controle!G:G,Controle!A:A,CONCAT("=",$V10),Controle!H:H,"=0") -> 0 | Y10: =SUMIFS(Controle!G:G,Controle!A:A,CONCAT("=",$V10)) -> 720 | AA10: =IFERROR(__xludf.DUMMYFUNCTION("""COMPUTED_VALUE"""),"Mercado São José") -> Mercado São José | AB10: =SUMIFS(Controle!H:H,Controle!A:A,CONCAT("=",$AA10),Controle!I:I,"<>0") -> 67.64 | AD10: Luz | AE10: =SUMIFS(Controle!H:H,Controle!D:D,CONCAT("=",$AD10),Controle!I:I,"<>0") -> 7988.43
A11: Itaú | B11: =5088.84+(5088.84*0.041) -> 5297.4824 | C11: 0 | F11: =HYPERLINK("https://docs.google.com/spreadsheets/d/1Uj96w5r3n0cneD7LaJDh3hKPtO69t6MtHFm4lkQ5K7I/edit?gid=775169775#gid=775169775&range=A"&MATCH(E11,Controle!E:E,0),"Ir") -> #N/A | G11: =COUNTIF(Controle!E:E,CONCAT("=",E11)) -> 1214 | H11: =SUMIFS(Controle!G:G,Controle!E:E,CONCAT("=",$E11),Controle!H:H,"<>0") -> 0 | I11: =SUMIFS(Controle!G:G,Controle!E:E,CONCAT("=",$E11),Controle!H:H,"=0") -> 0 | J11: =SUMIFS(Controle!G:G,Controle!E:E,CONCAT("=",$E11)) -> 0 | L11: =IFERROR(__xludf.DUMMYFUNCTION("""COMPUTED_VALUE"""),"4/2027") -> 4/2027 | M11: =SUMIFS(Controle!G:G,Controle!F:F,CONCAT("=",$L11),Controle!H:H,"=0") -> 4219.71 | N11: =SUMIFS(Controle!H:H,Controle!F:F,CONCAT("=",$L11),Controle!I:I,"<>") -> 901.22 | O11: =IF(M11>N11,M11-N11,0) -> 3318.49 | Q11: =IFERROR(__xludf.DUMMYFUNCTION("""COMPUTED_VALUE"""),"Financiamento Santander") -> Financiamento Santander | R11: =SUMIFS(Controle!G:G,Controle!A:A,CONCAT("=",$Q11),Controle!H:H,"<>0") -> 751.83 | S11: =SUMIFS(Controle!G:G,Controle!A:A,CONCAT("=",$Q11),Controle!H:H,"=0") -> 0 | T11: =SUMIFS(Controle!G:G,Controle!A:A,CONCAT("=",$Q11)) -> 751.83 | V11: =IFERROR(__xludf.DUMMYFUNCTION("""COMPUTED_VALUE"""),"Pé na Estrada") -> Pé na Estrada | W11: =SUMIFS(Controle!G:G,Controle!A:A,CONCAT("=",$V11),Controle!H:H,"<>0") -> 8692 | X11: =SUMIFS(Controle!G:G,Controle!A:A,CONCAT("=",$V11),Controle!H:H,"=0") -> 0 | Y11: =SUMIFS(Controle!G:G,Controle!A:A,CONCAT("=",$V11)) -> 8692 | AA11: =IFERROR(__xludf.DUMMYFUNCTION("""COMPUTED_VALUE"""),"Mercado Bom Preço") -> Mercado Bom Preço | AB11: =SUMIFS(Controle!H:H,Controle!A:A,CONCAT("=",$AA11),Controle!I:I,"<>0") -> 74.24 | AD11: Mercado | AE11: =SUMIFS(Controle!H:H,Controle!D:D,CONCAT("=",$AD11),Controle!I:I,"<>0") -> 571.85
A12: Nubank | B12: 0 | F12: =HYPERLINK("https://docs.google.com/spreadsheets/d/1Uj96w5r3n0cneD7LaJDh3hKPtO69t6MtHFm4lkQ5K7I/edit?gid=775169775#gid=775169775&range=A"&MATCH(E12,Controle!E:E,0),"Ir") -> #N/A | G12: =COUNTIF(Controle!E:E,CONCAT("=",E12)) -> 1214 | H12: =SUMIFS(Controle!G:G,Controle!E:E,CONCAT("=",$E12),Controle!H:H,"<>0") -> 0 | I12: =SUMIFS(Controle!G:G,Controle!E:E,CONCAT("=",$E12),Controle!H:H,"=0") -> 0 | J12: =SUMIFS(Controle!G:G,Controle!E:E,CONCAT("=",$E12)) -> 0 | L12: =IFERROR(__xludf.DUMMYFUNCTION("""COMPUTED_VALUE"""),"5/2027") -> 5/2027 | M12: =SUMIFS(Controle!G:G,Controle!F:F,CONCAT("=",$L12),Controle!H:H,"=0") -> 4219.71 | N12: =SUMIFS(Controle!H:H,Controle!F:F,CONCAT("=",$L12),Controle!I:I,"<>") -> 901.22 | O12: =IF(M12>N12,M12-N12,0) -> 3318.49 | Q12: =IFERROR(__xludf.DUMMYFUNCTION("""COMPUTED_VALUE"""),"Financiamento Tucson") -> Financiamento Tucson | R12: =SUMIFS(Controle!G:G,Controle!A:A,CONCAT("=",$Q12),Controle!H:H,"<>0") -> 2473.56 | S12: =SUMIFS(Controle!G:G,Controle!A:A,CONCAT("=",$Q12),Controle!H:H,"=0") -> 1236.78 | T12: =SUMIFS(Controle!G:G,Controle!A:A,CONCAT("=",$Q12)) -> 3710.34 | V12: =IFERROR(__xludf.DUMMYFUNCTION("""COMPUTED_VALUE"""),"C. F. Menezes & Carvalho Ltda - Qualitche") -> C. F. Menezes & Carvalho Ltda - Qualitche | W12: =SUMIFS(Controle!G:G,Controle!A:A,CONCAT("=",$V12),Controle!H:H,"<>0") -> 1840 | X12: =SUMIFS(Controle!G:G,Controle!A:A,CONCAT("=",$V12),Controle!H:H,"=0") -> 0 | Y12: =SUMIFS(Controle!G:G,Controle!A:A,CONCAT("=",$V12)) -> 1840 | AA12: =IFERROR(__xludf.DUMMYFUNCTION("""COMPUTED_VALUE"""),"Posto Fox") -> Posto Fox | AB12: =SUMIFS(Controle!H:H,Controle!A:A,CONCAT("=",$AA12),Controle!I:I,"<>0") -> 100 | AD12: Seguro | AE12: =SUMIFS(Controle!H:H,Controle!D:D,CONCAT("=",$AD12),Controle!I:I,"<>0") -> 1715.8
A13: CEF | B13: 0 | F13: =HYPERLINK("https://docs.google.com/spreadsheets/d/1Uj96w5r3n0cneD7LaJDh3hKPtO69t6MtHFm4lkQ5K7I/edit?gid=775169775#gid=775169775&range=A"&MATCH(E13,Controle!E:E,0),"Ir") -> #N/A | G13: =COUNTIF(Controle!E:E,CONCAT("=",E13)) -> 1214 | H13: =SUMIFS(Controle!G:G,Controle!E:E,CONCAT("=",$E13),Controle!H:H,"<>0") -> 0 | I13: =SUMIFS(Controle!G:G,Controle!E:E,CONCAT("=",$E13),Controle!H:H,"=0") -> 0 | J13: =SUMIFS(Controle!G:G,Controle!E:E,CONCAT("=",$E13)) -> 0 | L13: =IFERROR(__xludf.DUMMYFUNCTION("""COMPUTED_VALUE"""),"6/2027") -> 6/2027 | M13: =SUMIFS(Controle!G:G,Controle!F:F,CONCAT("=",$L13),Controle!H:H,"=0") -> 4219.71 | N13: =SUMIFS(Controle!H:H,Controle!F:F,CONCAT("=",$L13),Controle!I:I,"<>") -> 901.22 | O13: =IF(M13>N13,M13-N13,0) -> 3318.49 | R13: =SUMIFS(Controle!G:G,Controle!A:A,CONCAT("=",$Q13),Controle!H:H,"<>0") -> 0 | S13: =SUMIFS(Controle!G:G,Controle!A:A,CONCAT("=",$Q13),Controle!H:H,"=0") -> 0 | T13: =SUMIFS(Controle!G:G,Controle!A:A,CONCAT("=",$Q13)) -> 0 | V13: =IFERROR(__xludf.DUMMYFUNCTION("""COMPUTED_VALUE"""),"Calçados para Dança - Vuollo") -> Calçados para Dança - Vuollo | W13: =SUMIFS(Controle!G:G,Controle!A:A,CONCAT("=",$V13),Controle!H:H,"<>0") -> 3318 | X13: =SUMIFS(Controle!G:G,Controle!A:A,CONCAT("=",$V13),Controle!H:H,"=0") -> 0 | Y13: =SUMIFS(Controle!G:G,Controle!A:A,CONCAT("=",$V13)) -> 3318 | AA13: =IFERROR(__xludf.DUMMYFUNCTION("""COMPUTED_VALUE"""),"Mercado D'amille") -> Mercado D'amille | AB13: =SUMIFS(Controle!H:H,Controle!A:A,CONCAT("=",$AA13),Controle!I:I,"<>0") -> 340.07 | AD13: Selecione | AE13: =SUMIFS(Controle!H:H,Controle!D:D,CONCAT("=",$AD13),Controle!I:I,"<>0") -> 2473.56
A14: Carteira | B14: 0 | F14: =HYPERLINK("https://docs.google.com/spreadsheets/d/1Uj96w5r3n0cneD7LaJDh3hKPtO69t6MtHFm4lkQ5K7I/edit?gid=775169775#gid=775169775&range=A"&MATCH(E14,Controle!E:E,0),"Ir") -> #N/A | G14: =COUNTIF(Controle!E:E,CONCAT("=",E14)) -> 1214 | H14: =SUMIFS(Controle!G:G,Controle!E:E,CONCAT("=",$E14),Controle!H:H,"<>0") -> 0 | I14: =SUMIFS(Controle!G:G,Controle!E:E,CONCAT("=",$E14),Controle!H:H,"=0") -> 0 | J14: =SUMIFS(Controle!G:G,Controle!E:E,CONCAT("=",$E14)) -> 0 | R14: =SUMIFS(Controle!G:G,Controle!A:A,CONCAT("=",$Q14),Controle!H:H,"<>0") -> 0 | S14: =SUMIFS(Controle!G:G,Controle!A:A,CONCAT("=",$Q14),Controle!H:H,"=0") -> 0 | T14: =SUMIFS(Controle!G:G,Controle!A:A,CONCAT("=",$Q14)) -> 0 | V14: =IFERROR(__xludf.DUMMYFUNCTION("""COMPUTED_VALUE"""),"Montana") -> Montana | W14: =SUMIFS(Controle!G:G,Controle!A:A,CONCAT("=",$V14),Controle!H:H,"<>0") -> 2102.75 | X14: =SUMIFS(Controle!G:G,Controle!A:A,CONCAT("=",$V14),Controle!H:H,"=0") -> 0 | Y14: =SUMIFS(Controle!G:G,Controle!A:A,CONCAT("=",$V14)) -> 2102.75 | AA14: =IFERROR(__xludf.DUMMYFUNCTION("""COMPUTED_VALUE"""),"Tênis Cruz Machado") -> Tênis Cruz Machado | AB14: =SUMIFS(Controle!H:H,Controle!A:A,CONCAT("=",$AA14),Controle!I:I,"<>0") -> 89.9 | AD14: Telefonia | AE14: =SUMIFS(Controle!H:H,Controle!D:D,CONCAT("=",$AD14),Controle!I:I,"<>0") -> 1297.88
A15: Caixa | B15: 0 | F15: =HYPERLINK("https://docs.google.com/spreadsheets/d/1Uj96w5r3n0cneD7LaJDh3hKPtO69t6MtHFm4lkQ5K7I/edit?gid=775169775#gid=775169775&range=A"&MATCH(E15,Controle!E:E,0),"Ir") -> #N/A | G15: =COUNTIF(Controle!E:E,CONCAT("=",E15)) -> 1214 | H15: =SUMIFS(Controle!G:G,Controle!E:E,CONCAT("=",$E15),Controle!H:H,"<>0") -> 0 | I15: =SUMIFS(Controle!G:G,Controle!E:E,CONCAT("=",$E15),Controle!H:H,"=0") -> 0 | J15: =SUMIFS(Controle!G:G,Controle!E:E,CONCAT("=",$E15)) -> 0 | R15: =SUMIFS(Controle!G:G,Controle!A:A,CONCAT("=",$Q15),Controle!H:H,"<>0") -> 0 | S15: =SUMIFS(Controle!G:G,Controle!A:A,CONCAT("=",$Q15),Controle!H:H,"=0") -> 0 | T15: =SUMIFS(Controle!G:G,Controle!A:A,CONCAT("=",$Q15)) -> 0 | V15: =IFERROR(__xludf.DUMMYFUNCTION("""COMPUTED_VALUE"""),"E R Confecções - Chapéu Gaucho") -> E R Confecções - Chapéu Gaucho | W15: =SUMIFS(Controle!G:G,Controle!A:A,CONCAT("=",$V15),Controle!H:H,"<>0") -> 758.78 | X15: =SUMIFS(Controle!G:G,Controle!A:A,CONCAT("=",$V15),Controle!H:H,"=0") -> 0 | Y15: =SUMIFS(Controle!G:G,Controle!A:A,CONCAT("=",$V15)) -> 758.78 | AA15: =IFERROR(__xludf.DUMMYFUNCTION("""COMPUTED_VALUE"""),"Pampasul") -> Pampasul | AB15: =SUMIFS(Controle!H:H,Controle!A:A,CONCAT("=",$AA15),Controle!I:I,"<>0") -> 9005.58 | AE15: =SUMIFS(Controle!H:H,Controle!D:D,CONCAT("=",$AD15),Controle!I:I,"<>0") -> 0
A16: Caju | B16: 396.37 | F16: =HYPERLINK("https://docs.google.com/spreadsheets/d/1Uj96w5r3n0cneD7LaJDh3hKPtO69t6MtHFm4lkQ5K7I/edit?gid=775169775#gid=775169775&range=A"&MATCH(E16,Controle!E:E,0),"Ir") -> #N/A | G16: =COUNTIF(Controle!E:E,CONCAT("=",E16)) -> 1214 | H16: =SUMIFS(Controle!G:G,Controle!E:E,CONCAT("=",$E16),Controle!H:H,"<>0") -> 0 | I16: =SUMIFS(Controle!G:G,Controle!E:E,CONCAT("=",$E16),Controle!H:H,"=0") -> 0 | J16: =SUMIFS(Controle!G:G,Controle!E:E,CONCAT("=",$E16)) -> 0 | R16: =SUMIFS(Controle!G:G,Controle!A:A,CONCAT("=",$Q16),Controle!H:H,"<>0") -> 0 | S16: =SUMIFS(Controle!G:G,Controle!A:A,CONCAT("=",$Q16),Controle!H:H,"=0") -> 0 | T16: =SUMIFS(Controle!G:G,Controle!A:A,CONCAT("=",$Q16)) -> 0 | V16: =IFERROR(__xludf.DUMMYFUNCTION("""COMPUTED_VALUE"""),"Pura Raça") -> Pura Raça | W16: =SUMIFS(Controle!G:G,Controle!A:A,CONCAT("=",$V16),Controle!H:H,"<>0") -> 5885.97 | X16: =SUMIFS(Controle!G:G,Controle!A:A,CONCAT("=",$V16),Controle!H:H,"=0") -> 0 | Y16: =SUMIFS(Controle!G:G,Controle!A:A,CONCAT("=",$V16)) -> 5885.97 | AE16: =SUMIFS(Controle!H:H,Controle!D:D,CONCAT("=",$AD16),Controle!I:I,"<>0") -> 0
F17: =HYPERLINK("https://docs.google.com/spreadsheets/d/1Uj96w5r3n0cneD7LaJDh3hKPtO69t6MtHFm4lkQ5K7I/edit?gid=775169775#gid=775169775&range=A"&MATCH(E17,Controle!E:E,0),"Ir") -> #N/A | G17: =COUNTIF(Controle!E:E,CONCAT("=",E17)) -> 1214 | H17: =SUMIFS(Controle!G:G,Controle!E:E,CONCAT("=",$E17),Controle!H:H,"<>0") -> 0 | I17: =SUMIFS(Controle!G:G,Controle!E:E,CONCAT("=",$E17),Controle!H:H,"=0") -> 0 | J17: =SUMIFS(Controle!G:G,Controle!E:E,CONCAT("=",$E17)) -> 0 | R17: =SUMIFS(Controle!G:G,Controle!A:A,CONCAT("=",$Q17),Controle!H:H,"<>0") -> 0 | S17: =SUMIFS(Controle!G:G,Controle!A:A,CONCAT("=",$Q17),Controle!H:H,"=0") -> 0 | T17: =SUMIFS(Controle!G:G,Controle!A:A,CONCAT("=",$Q17)) -> 0 | V17: =IFERROR(__xludf.DUMMYFUNCTION("""COMPUTED_VALUE"""),"Black") -> Black | W17: =SUMIFS(Controle!G:G,Controle!A:A,CONCAT("=",$V17),Controle!H:H,"<>0") -> 541.2 | X17: =SUMIFS(Controle!G:G,Controle!A:A,CONCAT("=",$V17),Controle!H:H,"=0") -> 0 | Y17: =SUMIFS(Controle!G:G,Controle!A:A,CONCAT("=",$V17)) -> 541.2 | AE17: =SUMIFS(Controle!H:H,Controle!D:D,CONCAT("=",$AD17),Controle!I:I,"<>0") -> 0
A18: Total | B18: =SUM(B8:B17) -> 6972.6224 | F18: =HYPERLINK("https://docs.google.com/spreadsheets/d/1Uj96w5r3n0cneD7LaJDh3hKPtO69t6MtHFm4lkQ5K7I/edit?gid=775169775#gid=775169775&range=A"&MATCH(E18,Controle!E:E,0),"Ir") -> #N/A | G18: =COUNTIF(Controle!E:E,CONCAT("=",E18)) -> 1214 | H18: =SUMIFS(Controle!G:G,Controle!E:E,CONCAT("=",$E18),Controle!H:H,"<>0") -> 0 | I18: =SUMIFS(Controle!G:G,Controle!E:E,CONCAT("=",$E18),Controle!H:H,"=0") -> 0 | J18: =SUMIFS(Controle!G:G,Controle!E:E,CONCAT("=",$E18)) -> 0 | R18: =SUMIFS(Controle!G:G,Controle!A:A,CONCAT("=",$Q18),Controle!H:H,"<>0") -> 0 | S18: =SUMIFS(Controle!G:G,Controle!A:A,CONCAT("=",$Q18),Controle!H:H,"=0") -> 0 | T18: =SUMIFS(Controle!G:G,Controle!A:A,CONCAT("=",$Q18)) -> 0 | W18: =SUMIFS(Controle!G:G,Controle!A:A,CONCAT("=",$V18),Controle!H:H,"<>0") -> 0 | X18: =SUMIFS(Controle!G:G,Controle!A:A,CONCAT("=",$V18),Controle!H:H,"=0") -> 0 | Y18: =SUMIFS(Controle!G:G,Controle!A:A,CONCAT("=",$V18)) -> 0 | AE18: =SUMIFS(Controle!H:H,Controle!D:D,CONCAT("=",$AD18),Controle!I:I,"<>0") -> 0
A19: Diferenca | B19: =B18-B3 -> -2401.2376 | C19: =SUM(C8:C18)+B19 -> -1015.5076 | F19: =HYPERLINK("https://docs.google.com/spreadsheets/d/1Uj96w5r3n0cneD7LaJDh3hKPtO69t6MtHFm4lkQ5K7I/edit?gid=775169775#gid=775169775&range=A"&MATCH(E19,Controle!E:E,0),"Ir") -> #N/A | G19: =COUNTIF(Controle!E:E,CONCAT("=",E19)) -> 1214 | H19: =SUMIFS(Controle!G:G,Controle!E:E,CONCAT("=",$E19),Controle!H:H,"<>0") -> 0 | I19: =SUMIFS(Controle!G:G,Controle!E:E,CONCAT("=",$E19),Controle!H:H,"=0") -> 0 | J19: =SUMIFS(Controle!G:G,Controle!E:E,CONCAT("=",$E19)) -> 0 | R19: =SUMIFS(Controle!G:G,Controle!A:A,CONCAT("=",$Q19),Controle!H:H,"<>0") -> 0 | S19: =SUMIFS(Controle!G:G,Controle!A:A,CONCAT("=",$Q19),Controle!H:H,"=0") -> 0 | T19: =SUMIFS(Controle!G:G,Controle!A:A,CONCAT("=",$Q19)) -> 0 | W19: =SUMIFS(Controle!G:G,Controle!A:A,CONCAT("=",$V19),Controle!H:H,"<>0") -> 0 | X19: =SUMIFS(Controle!G:G,Controle!A:A,CONCAT("=",$V19),Controle!H:H,"=0") -> 0 | Y19: =SUMIFS(Controle!G:G,Controle!A:A,CONCAT("=",$V19)) -> 0 | AE19: =SUMIFS(Controle!H:H,Controle!D:D,CONCAT("=",$AD19),Controle!I:I,"<>0") -> 0
A22: Usado | B22: Parcela | C22: Column 8 | D22: Vezes | E22: Pendentes | F22: Total Pendente | G22: Pagas | H22: Total Pago
A23: 45524 | B23: 1210.7 | D23: 10 | E23: =IF($A23,IF(IFERROR(DATEDIF($A23,CONCAT("01/",Mês_atual[[#HEADERS],[9/2026]]),"M"),0)<$D23,$D23-IFERROR(IFERROR(DATEDIF($A23,CONCAT("01/",Mês_atual[[#HEADERS],[9/2026]]),"M"),0),0),0),"") -> 0 | F23: =E23*B23 -> 0 | G23: =D23-E23 -> 10 | H23: =G23*B23 -> 12107 | L23: 1683.09
A24: 45558 | B24: 1250 | D24: 12 | E24: =IF($A24,IF(IFERROR(DATEDIF($A24,CONCAT("01/",Mês_atual[[#HEADERS],[9/2026]]),"M"),0)<$D24,$D24-IFERROR(IFERROR(DATEDIF($A24,CONCAT("01/",Mês_atual[[#HEADERS],[9/2026]]),"M"),0),0),0),"") -> 0 | F24: =E24*B24 -> 0 | G24: =D24-E24 -> 12 | H24: =G24*B24 -> 15000 | L24: 2965.46
A25: 45586 | B25: 1216.96 | D25: 10 | E25: =IF($A25,IF(IFERROR(DATEDIF($A25,CONCAT("01/",Mês_atual[[#HEADERS],[9/2026]]),"M"),0)<$D25,$D25-IFERROR(IFERROR(DATEDIF($A25,CONCAT("01/",Mês_atual[[#HEADERS],[9/2026]]),"M"),0),0),0),"") -> 0 | F25: =E25*B25 -> 0 | G25: =D25-E25 -> 10 | H25: =G25*B25 -> 12169.6 | L25: 500
A26: 45617 | B26: 1062.21 | D26: 10 | E26: =IF($A26,IF(IFERROR(DATEDIF($A26,CONCAT("01/",Mês_atual[[#HEADERS],[9/2026]]),"M"),0)<$D26,$D26-IFERROR(IFERROR(DATEDIF($A26,CONCAT("01/",Mês_atual[[#HEADERS],[9/2026]]),"M"),0),0),0),"") -> 0 | F26: =E26*B26 -> 0 | G26: =D26-E26 -> 10 | H26: =G26*B26 -> 10622.1 | L26: 160
A27: 45645 | B27: 1021.03 | D27: 10 | E27: =IF($A27,IF(IFERROR(DATEDIF($A27,CONCAT("01/",Mês_atual[[#HEADERS],[9/2026]]),"M"),0)<$D27,$D27-IFERROR(IFERROR(DATEDIF($A27,CONCAT("01/",Mês_atual[[#HEADERS],[9/2026]]),"M"),0),0),0),"") -> 0 | F27: =E27*B27 -> 0 | G27: =D27-E27 -> 10 | H27: =G27*B27 -> 10210.3 | L27: 300
A28: 45678 | B28: 583.95 | D28: 12 | E28: =IF($A28,IF(IFERROR(DATEDIF($A28,CONCAT("01/",Mês_atual[[#HEADERS],[9/2026]]),"M"),0)<$D28,$D28-IFERROR(IFERROR(DATEDIF($A28,CONCAT("01/",Mês_atual[[#HEADERS],[9/2026]]),"M"),0),0),0),"") -> 0 | F28: =E28*B28 -> 0 | G28: =D28-E28 -> 12 | H28: =G28*B28 -> 7007.4 | L28: =L23-(L24+L25+L26+L27) -> -2242.37
A29: 45708 | B29: 683.23 | D29: 12 | E29: =IF($A29,IF(IFERROR(DATEDIF($A29,CONCAT("01/",Mês_atual[[#HEADERS],[9/2026]]),"M"),0)<$D29,$D29-IFERROR(IFERROR(DATEDIF($A29,CONCAT("01/",Mês_atual[[#HEADERS],[9/2026]]),"M"),0),0),0),"") -> 0 | F29: =E29*B29 -> 0 | G29: =D29-E29 -> 12 | H29: =G29*B29 -> 8198.76
A30: 45740 | B30: 681.26 | D30: 10 | E30: =IF($A30,IF(IFERROR(DATEDIF($A30,CONCAT("01/",Mês_atual[[#HEADERS],[9/2026]]),"M"),0)<$D30,$D30-IFERROR(IFERROR(DATEDIF($A30,CONCAT("01/",Mês_atual[[#HEADERS],[9/2026]]),"M"),0),0),0),"") -> 0 | F30: =E30*B30 -> 0 | G30: =D30-E30 -> 10 | H30: =G30*B30 -> 6812.6
A31: 45771 | B31: 694.8 | D31: 10 | E31: =IF($A31,IF(IFERROR(DATEDIF($A31,CONCAT("01/",Mês_atual[[#HEADERS],[9/2026]]),"M"),0)<$D31,$D31-IFERROR(IFERROR(DATEDIF($A31,CONCAT("01/",Mês_atual[[#HEADERS],[9/2026]]),"M"),0),0),0),"") -> 0 | F31: =E31*B31 -> 0 | G31: =D31-E31 -> 10 | H31: =G31*B31 -> 6948
A32: 45800 | B32: 700 | D32: 10 | E32: =IF($A32,IF(IFERROR(DATEDIF($A32,CONCAT("01/",Mês_atual[[#HEADERS],[9/2026]]),"M"),0)<$D32,$D32-IFERROR(IFERROR(DATEDIF($A32,CONCAT("01/",Mês_atual[[#HEADERS],[9/2026]]),"M"),0),0),0),"") -> 0 | F32: =E32*B32 -> 0 | G32: =D32-E32 -> 10 | H32: =G32*B32 -> 7000
A33: 45832 | B33: 500 | D33: 10 | E33: =IF($A33,IF(IFERROR(DATEDIF($A33,CONCAT("01/",Mês_atual[[#HEADERS],[9/2026]]),"M"),0)<$D33,$D33-IFERROR(IFERROR(DATEDIF($A33,CONCAT("01/",Mês_atual[[#HEADERS],[9/2026]]),"M"),0),0),0),"") -> 0 | F33: =E33*B33 -> 0 | G33: =D33-E33 -> 10 | H33: =G33*B33 -> 5000
A34: 45861 | B34: 800 | D34: 10 | E34: =IF($A34,IF(IFERROR(DATEDIF($A34,CONCAT("01/",Mês_atual[[#HEADERS],[9/2026]]),"M"),0)<$D34,$D34-IFERROR(IFERROR(DATEDIF($A34,CONCAT("01/",Mês_atual[[#HEADERS],[9/2026]]),"M"),0),0),0),"") -> 0 | F34: =E34*B34 -> 0 | G34: =D34-E34 -> 10 | H34: =G34*B34 -> 8000
A35: 45892 | B35: 700 | D35: 12 | E35: =IF($A35,IF(IFERROR(DATEDIF($A35,CONCAT("01/",Mês_atual[[#HEADERS],[9/2026]]),"M"),0)<$D35,$D35-IFERROR(IFERROR(DATEDIF($A35,CONCAT("01/",Mês_atual[[#HEADERS],[9/2026]]),"M"),0),0),0),"") -> 0 | F35: =E35*B35 -> 0 | G35: =D35-E35 -> 12 | H35: =G35*B35 -> 8400
A36: 45923 | B36: 1000 | D36: 12 | E36: =IF($A36,IF(IFERROR(DATEDIF($A36,CONCAT("01/",Mês_atual[[#HEADERS],[9/2026]]),"M"),0)<$D36,$D36-IFERROR(IFERROR(DATEDIF($A36,CONCAT("01/",Mês_atual[[#HEADERS],[9/2026]]),"M"),0),0),0),"") -> 1 | F36: =E36*B36 -> 1000 | G36: =D36-E36 -> 11 | H36: =G36*B36 -> 11000
A37: 45952 | B37: 791.74 | D37: 12 | E37: =IF($A37,IF(IFERROR(DATEDIF($A37,CONCAT("01/",Mês_atual[[#HEADERS],[9/2026]]),"M"),0)<$D37,$D37-IFERROR(IFERROR(DATEDIF($A37,CONCAT("01/",Mês_atual[[#HEADERS],[9/2026]]),"M"),0),0),0),"") -> 2 | F37: =E37*B37 -> 1583.48 | G37: =D37-E37 -> 10 | H37: =G37*B37 -> 7917.4
B38: =SUMIF(Santander[Pendentes],">0",Santander[Parcela]) -> 1791.74 | F38: =SUM(F23:F37) -> 2583.48 | H38: =SUM(H23:H35) -> 117475.76
A41: Usado | B41: Parcela | C41: Column 8 | D41: Vezes | E41: Pendentes | F41: Total Pendente | G41: Pagas | H41: Total Pago
A42: 45952 | B42: 250 | D42: 12 | E42: =IF($A42,IF(IFERROR(DATEDIF($A42,CONCAT("01/",Mês_atual[[#HEADERS],[9/2026]]),"M"),0)<$D42,$D42-IFERROR(DATEDIF($A42,CONCAT("01/",Mês_atual[[#HEADERS],[9/2026]]),"M"),0),0),"") -> 2 | F42: =E42*B42 -> 500 | G42: =D42-E42 -> 10 | H42: =G42*B42 -> 2500
A43: 45885 | B43: 300 | D43: 10 | E43: =IF($A43,IF(IFERROR(DATEDIF($A43,CONCAT("01/",Mês_atual[[#HEADERS],[9/2026]]),"M"),0)<$D43,$D43-IFERROR(DATEDIF($A43,CONCAT("01/",Mês_atual[[#HEADERS],[9/2026]]),"M"),0),0),"") -> 0 | F43: =E43*B43 -> 0 | G43: =D43-E43 -> 10 | H43: =G43*B43 -> 3000
A44: 45771 | B44: 400 | D44: 5 | E44: =IF($A44,IF(IFERROR(DATEDIF($A44,CONCAT("01/",Mês_atual[[#HEADERS],[9/2026]]),"M"),0)<$D44,$D44-IFERROR(DATEDIF($A44,CONCAT("01/",Mês_atual[[#HEADERS],[9/2026]]),"M"),0),0),"") -> 0 | F44: =E44*B44 -> 0 | G44: =D44-E44 -> 5 | H44: =G44*B44 -> 2000
A45: 45682 | B45: 300.7 | D45: 10 | E45: =IF($A45,IF(IFERROR(DATEDIF($A45,CONCAT("01/",Mês_atual[[#HEADERS],[9/2026]]),"M"),0)<$D45,$D45-IFERROR(DATEDIF($A45,CONCAT("01/",Mês_atual[[#HEADERS],[9/2026]]),"M"),0),0),"") -> 0 | F45: =E45*B45 -> 0 | G45: =D45-E45 -> 10 | H45: =G45*B45 -> 3007
A46: 45677 | B46: 333.37 | D46: 12 | E46: =IF($A46,IF(IFERROR(DATEDIF($A46,CONCAT("01/",Mês_atual[[#HEADERS],[9/2026]]),"M"),0)<$D46,$D46-IFERROR(DATEDIF($A46,CONCAT("01/",Mês_atual[[#HEADERS],[9/2026]]),"M"),0),0),"") -> 0 | F46: =E46*B46 -> 0 | G46: =D46-E46 -> 12 | H46: =G46*B46 -> 4000.44
A47: 25/08/2025 | B47: R$ 533.34 | D47: 3 | E47: =IF($A47,IF(IFERROR(DATEDIF($A47,CONCAT("01/",Dashboard!$B$1),"M"),0)<$D47,$D47-IFERROR(DATEDIF($A47,CONCAT("01/",Dashboard!$B$1),"M"),0),0),"") -> 0 | F47: =E47*B47 -> 0 | G47: =D47-E47 -> 3 | H47: =G47*B47 -> 1600.02
B48: =SUMIF(Itaú[Pendentes],">0",Itaú[Parcela]) -> 250 | F48: =SUM(F42:F47) -> 500 | H48: =SUM(H43:H46) -> 12007.44
A51: Usado | B51: Parcela | C51: Column 8 | D51: Vezes | E51: Pendentes | F51: Total Pendente | G51: Pagas | H51: Total Pago
A52: 45946 | B52: 300 | D52: 10 | E52: =IF($A52,IF(IFERROR(DATEDIF($A52,CONCAT("01/",Mês_atual[[#HEADERS],[9/2026]]),"M"),0)<$D52,$D52-IFERROR(DATEDIF($A52,CONCAT("01/",Mês_atual[[#HEADERS],[9/2026]]),"M"),0),0),"") -> 0 | F52: =E52*B52 -> 0 | G52: =D52-E52 -> 10 | H52: =G52*B52 -> 3000
A53: 45823 | B53: 500 | D53: 10 | E53: =IF($A53,IF(IFERROR(DATEDIF($A53,CONCAT("01/",Mês_atual[[#HEADERS],[9/2026]]),"M"),0)<$D53,$D53-IFERROR(DATEDIF($A53,CONCAT("01/",Mês_atual[[#HEADERS],[9/2026]]),"M"),0),0),"") -> 0 | F53: =E53*B53 -> 0 | G53: =D53-E53 -> 10 | H53: =G53*B53 -> 5000
A54: 45698 | B54: 250 | D54: 10 | E54: =IF($A54,IF(IFERROR(DATEDIF($A54,CONCAT("01/",Mês_atual[[#HEADERS],[9/2026]]),"M"),0)<$D54,$D54-IFERROR(DATEDIF($A54,CONCAT("01/",Mês_atual[[#HEADERS],[9/2026]]),"M"),0),0),"") -> 0 | F54: =E54*B54 -> 0 | G54: =D54-E54 -> 10 | H54: =G54*B54 -> 2500
A55: 45635 | B55: 225.75 | D55: 10 | E55: =IF($A55,IF(IFERROR(DATEDIF($A55,CONCAT("01/",Mês_atual[[#HEADERS],[9/2026]]),"M"),0)<$D55,$D55-IFERROR(DATEDIF($A55,CONCAT("01/",Mês_atual[[#HEADERS],[9/2026]]),"M"),0),0),"") -> 0 | F55: =E55*B55 -> 0 | G55: =D55-E55 -> 10 | H55: =G55*B55 -> 2257.5
A56: 45607 | B56: 350 | D56: 10 | E56: =IF($A56,IF(IFERROR(DATEDIF($A56,CONCAT("01/",Mês_atual[[#HEADERS],[9/2026]]),"M"),0)<$D56,$D56-IFERROR(DATEDIF($A56,CONCAT("01/",Mês_atual[[#HEADERS],[9/2026]]),"M"),0),0),"") -> 0 | F56: =E56*B56 -> 0 | G56: =D56-E56 -> 10 | H56: =G56*B56 -> 3500
A57: 45588 | B57: 350 | D57: 10 | E57: =IF($A57,IF(IFERROR(DATEDIF($A57,CONCAT("01/",Mês_atual[[#HEADERS],[9/2026]]),"M"),0)<$D57,$D57-IFERROR(DATEDIF($A57,CONCAT("01/",Mês_atual[[#HEADERS],[9/2026]]),"M"),0),0),"") -> 0 | F57: =E57*B57 -> 0 | G57: =D57-E57 -> 10 | H57: =G57*B57 -> 3500
A58: 15/10/2024 | B58: R$ 216.67 | D58: 3 | E58: =IF($A58,IF(IFERROR(DATEDIF($A58,CONCAT("01/",Mês_atual[[#HEADERS],[9/2026]]),"M"),0)<$D58,$D58-IFERROR(DATEDIF($A58,CONCAT("01/",Mês_atual[[#HEADERS],[9/2026]]),"M"),0),0),"") -> 0 | F58: =E58*B58 -> 0 | G58: =D58-E58 -> 3 | H58: =G58*B58 -> 650.01
B59: =SUMIF(Nubank[Pendentes],">0",Nubank[Parcela]) -> 0 | F59: =SUM(F52:F58) -> 0 | H59: =SUM(H53:H58) -> 17407.51

Sheet Controle
A1: Conta | B1: Local | C1: Tipo | D1: Categoria | E1: Vencimento | F1: Mês | G1: Valor | H1: Valor Pago | I1: Data Pagamento | J1: Coluna 2 | K1: Coluna 3 | L1: Coluna 4 | M1: Coluna 5 | N1: Coluna 6 | O1: Coluna 7 | P1: Coluna 8 | Q1: Coluna 9 | R1: Coluna 10 | S1: Coluna 11 | T1: Coluna 12 | U1: Coluna 13 | V1: Coluna 14 | W1: Coluna 15 | X1: Coluna 16 | Y1: Coluna 17 | Z1: Coluna 18 | AA1: Coluna 19 | AB1: Coluna 20 | AC1: Coluna 21 | AD1: Coluna 22
A2: Ademicon | B2: Casa | C2: Dívida | D2: Investimento | E2: 45001 | F2: =IF($E2,CONCATENATE(MONTH(E2),"/",YEAR(E2)),"") -> 3/2023 | G2: 649.6 | H2: =IF(I2,G2,0) -> 649.6 | I2: 45001
A3: Ademicon | B3: Casa | C3: Dívida | D3: Investimento | E3: 45024 | F3: =IF($E3,CONCATENATE(MONTH(E3),"/",YEAR(E3)),"") -> 4/2023 | G3: 649.6 | H3: =IF(I3,G3,0) -> 649.6 | I3: 45024
A4: Ademicon | B4: Casa | C4: Dívida | D4: Investimento | E4: 45054 | F4: =IF($E4,CONCATENATE(MONTH(E4),"/",YEAR(E4)),"") -> 5/2023 | G4: 649.6 | H4: =IF(I4,G4,0) -> 649.6 | I4: 45054
A5: Ademicon | B5: Casa | C5: Dívida | D5: Investimento | E5: 45085 | F5: =IF($E5,CONCATENATE(MONTH(E5),"/",YEAR(E5)),"") -> 6/2023 | G5: 649.6 | H5: =IF(I5,G5,0) -> 649.6 | I5: 45085
A6: Ademicon | B6: Casa | C6: Dívida | D6: Investimento | E6: 45115 | F6: =IF($E6,CONCATENATE(MONTH(E6),"/",YEAR(E6)),"") -> 7/2023 | G6: 649.6 | H6: =IF(I6,G6,0) -> 649.6 | I6: 45115
A7: Ademicon | B7: Casa | C7: Dívida | D7: Investimento | E7: 45146 | F7: =IF($E7,CONCATENATE(MONTH(E7),"/",YEAR(E7)),"") -> 8/2023 | G7: 649.6 | H7: =IF(I7,G7,0) -> 649.6 | I7: 45146
A8: Ademicon | B8: Casa | C8: Dívida | D8: Investimento | E8: 45177 | F8: =IF($E8,CONCATENATE(MONTH(E8),"/",YEAR(E8)),"") -> 9/2023 | G8: 649.6 | H8: =IF(I8,G8,0) -> 649.6 | I8: 45177
A9: Ademicon | B9: Casa | C9: Dívida | D9: Investimento | E9: 45207 | F9: =IF($E9,CONCATENATE(MONTH(E9),"/",YEAR(E9)),"") -> 10/2023 | G9: 649.6 | H9: =IF(I9,G9,0) -> 649.6 | I9: 45207
A10: Ademicon | B10: Casa | C10: Dívida | D10: Investimento | E10: 45238 | F10: =IF($E10,CONCATENATE(MONTH(E10),"/",YEAR(E10)),"") -> 11/2023 | G10: 649.6 | H10: =IF(I10,G10,0) -> 649.6 | I10: 45238
A11: Ademicon | B11: Casa | C11: Dívida | D11: Investimento | E11: 45268 | F11: =IF($E11,CONCATENATE(MONTH(E11),"/",YEAR(E11)),"") -> 12/2023 | G11: 649.6 | H11: =IF(I11,G11,0) -> 649.6 | I11: 45268
A12: Ademicon | B12: Casa | C12: Dívida | D12: Investimento | E12: 45299 | F12: =IF($E12,CONCATENATE(MONTH(E12),"/",YEAR(E12)),"") -> 1/2024 | G12: 666.95 | H12: =IF(I12,G12,0) -> 666.95 | I12: 45299
A13: Ademicon | B13: Casa | C13: Dívida | D13: Investimento | E13: 45330 | F13: =IF($E13,CONCATENATE(MONTH(E13),"/",YEAR(E13)),"") -> 2/2024 | G13: 666.95 | H13: =IF(I13,G13,0) -> 666.95 | I13: 45330
... A44: CC Santander | B44: Loja | C44: Dívida | D44: Investimento | E44: 45422 | F44: =IF($E44,CONCATENATE(MONTH(E44),"/",YEAR(E44)),"") -> 5/2024 | G44: 3236.86 | H44: =IF(I44,G44,0) -> 3236.86 | I44: 45422
A45: TIM | C45: Variavel | D45: Telefonia | E45: 45422 | F45: =IF($E45,CONCATENATE(MONTH(E45),"/",YEAR(E45)),"") -> 5/2024 | G45: 96.99 | H45: =IF(I45,G45,0) -> 96.99 | I45: 45422
A46: TIM | C46: Variavel | D46: Telefonia | E46: 45422 | F46: =IF($E46,CONCATENATE(MONTH(E46),"/",YEAR(E46)),"") -> 5/2024 | G46: 46.99 | H46: =IF(I46,G46,0) -> 46.99 | I46: 45422
A47: CC Cresol | C47: Dívida | D47: Investimento | E47: 45423 | F47: =IF($E47,CONCATENATE(MONTH(E47),"/",YEAR(E47)),"") -> 5/2024 | G47: 64.9 | H47: =IF(I47,G47,0) -> 64.9 | I47: 45423
A48: Pampasul | C48: Fornecedor | D48: Investimento | E48: 45427 | F48: =IF($E48,CONCATENATE(MONTH(E48),"/",YEAR(E48)),"") -> 5/2024 | G48: 936.28 | H48: =IF(I48,G48,0) -> 936.28 | I48: 45427
A49: Pampasul | C49: Fornecedor | D49: Investimento | E49: 45429 | F49: =IF($E49,CONCATENATE(MONTH(E49),"/",YEAR(E49)),"") -> 5/2024 | G49: 949.28 | H49: =IF(I49,G49,0) -> 949.28 | I49: 45429
A50: MEI | B50: GIS | C50: Variavel | D50: Imposto | E50: 45432 | F50: =IF($E50,CONCATENATE(MONTH(E50),"/",YEAR(E50)),"") -> 5/2024 | G50: 71.6 | H50: =IF(I50,G50,0) -> 71.6 | I50: 45432
A51: Botinas | C51: Fornecedor | D51: Investimento | E51: 45438 | F51: =IF($E51,CONCATENATE(MONTH(E51),"/",YEAR(E51)),"") -> 5/2024 | G51: 1000 | H51: =IF(I51,G51,0) -> 1000 | I51: 45438
A52: Sokolowski | C52: Fornecedor | D52: Investimento | E52: 45442 | F52: =IF($E52,CONCATENATE(MONTH(E52),"/",YEAR(E52)),"") -> 5/2024 | G52: 207.27 | H52: =IF(I52,G52,0) -> 207.27 | I52: 45442
A53: Copel | C53: Variavel | D53: Luz | E53: 45445 | F53: =IF($E53,CONCATENATE(MONTH(E53),"/",YEAR(E53)),"") -> 6/2024 | G53: 38.67 | H53: =IF(I53,G53,0) -> 38.67 | I53: 45445
A54: Ciarin | C54: Fornecedor | D54: Investimento | E54: 45450 | F54: =IF($E54,CONCATENATE(MONTH(E54),"/",YEAR(E54)),"") -> 6/2024 | G54: 292.61 | H54: =IF(I54,G54,0) -> 292.61 | I54: 45450
A55: Qualitchê | C55: Fornecedor | D55: Investimento | E55: 45451 | F55: =IF($E55,CONCATENATE(MONTH(E55),"/",YEAR(E55)),"") -> 6/2024 | G55: 881 | H55: =IF(I55,G55,0) -> 881 | I55: 45451
A56: CC Nubank | B56: Vinicius | C56: Dívida | D56: Investimento | E56: 45451 | F56: =IF($E56,CONCATENATE(MONTH(E56),"/",YEAR(E56)),"") -> 6/2024 | G56: 2294.92 | H56: =IF(I56,G56,0) -> 2294.92 | I56: 45451
A57: Sanepar | B57: Casa | C57: Variavel | D57: Água | E57: 45451 | F57: =IF($E57,CONCATENATE(MONTH(E57),"/",YEAR(E57)),"") -> 6/2024 | G57: 49.16 | H57: =IF(I57,G57,0) -> 49.16 | I57: 45451
A58: Ademicon | B58: Casa | C58: Dívida | D58: Investimento | E58: 45451 | F58: =IF($E58,CONCATENATE(MONTH(E58),"/",YEAR(E58)),"") -> 6/2024 | G58: 666.95 | H58: =IF(I58,G58,0) -> 666.95 | I58: 45451
A59: Aluguel | C59: Variavel | D59: Locação | E59: 45453 | F59: =IF($E59,CONCATENATE(MONTH(E59),"/",YEAR(E59)),"") -> 6/2024 | G59: 1000 | H59: =IF(I59,G59,0) -> 1000 | I59: 45453
A60: Meganet | C60: Variavel | D60: Internet | E60: 45453 | F60: =IF($E60,CONCATENATE(MONTH(E60),"/",YEAR(E60)),"") -> 6/2024 | G60: 129.9 | H60: =IF(I60,G60,0) -> 129.9 | I60: 45453
A61: Meganet | C61: Variavel | D61: Internet | E61: 45453 | F61: =IF($E61,CONCATENATE(MONTH(E61),"/",YEAR(E61)),"") -> 6/2024 | G61: 99.9 | H61: =IF(I61,G61,0) -> 99.9 | I61: 45453
A62: Sanepar | B62: Loja | C62: Variavel | D62: Água | E62: 45453 | F62: =IF($E62,CONCATENATE(MONTH(E62),"/",YEAR(E62)),"") -> 6/2024 | G62: 97.24 | H62: =IF(I62,G62,0) -> 97.24 | I62: 45453
A63: CC Santander | C63: Dívida | D63: Investimento | E63: 45453 | F63: =IF($E63,CONCATENATE(MONTH(E63),"/",YEAR(E63)),"") -> 6/2024 | G63: 10569.03 | H63: =IF(I63,G63,0) -> 10569.03 | I63: 45453
A64: Copel | C64: Variavel | D64: Luz | E64: 45453 | F64: =IF($E64,CONCATENATE(MONTH(E64),"/",YEAR(E64)),"") -> 6/2024 | G64: 143.41 | H64: =IF(I64,G64,0) -> 143.41 | I64: 45453
A65: TIM | C65: Variavel | D65: Telefonia | E65: 45453 | F65: =IF($E65,CONCATENATE(MONTH(E65),"/",YEAR(E65)),"") -> 6/2024 | G65: 96.99 | H65: =IF(I65,G65,0) -> 96.99 | I65: 45453
A66: TIM | C66: Variavel | D66: Telefonia | E66: 45453 | F66: =IF($E66,CONCATENATE(MONTH(E66),"/",YEAR(E66)),"") -> 6/2024 | G66: 49.99 | H66: =IF(I66,G66,0) -> 49.99 | I66: 45453
A67: CC Cresol | C67: Dívida | D67: Investimento | E67: 45454 | F67: =IF($E67,CONCATENATE(MONTH(E67),"/",YEAR(E67)),"") -> 6/2024 | G67: 339.95 | H67: =IF(I67,G67,0) -> 339.95 | I67: 45454
A68: Pampasul | C68: Fornecedor | D68: Investimento | E68: 45457 | F68: =IF($E68,CONCATENATE(MONTH(E68),"/",YEAR(E68)),"") -> 6/2024 | G68: 932.27 | H68: =IF(I68,G68,0) -> 932.27 | I68: 45457
A69: Empréstimo Cresol | C69: Dívida | D69: Dívida | E69: 45458 | F69: =IF($E69,CONCATENATE(MONTH(E69),"/",YEAR(E69)),"") -> 6/2024 | G69: 1015.63 | H69: =IF(I69,G69,0) -> 1015.63 | I69: 45458
A70: Pampasul | C70: Fornecedor | D70: Investimento | E70: 45460 | F70: =IF($E70,CONCATENATE(MONTH(E70),"/",YEAR(E70)),"") -> 6/2024 | G70: 949.28 | H70: =IF(I70,G70,0) -> 949.28 | I70: 45460
A71: MEI | B71: GIS | C71: Variavel | D71: Imposto | E71: 45463 | F71: =IF($E71,CONCATENATE(MONTH(E71),"/",YEAR(E71)),"") -> 6/2024 | G71: 71.6 | H71: =IF(I71,G71,0) -> 71.6 | I71: 45463
A72: CC Nubank | B72: Gislaine | C72: Dívida | D72: Investimento | E72: 45467 | F72: =IF($E72,CONCATENATE(MONTH(E72),"/",YEAR(E72)),"") -> 6/2024 | G72: 90 | H72: =IF(I72,G72,0) -> 90 | I72: 45467
A73: Copel | C73: Variavel | D73: Luz | E73: 45475 | F73: =IF($E73,CONCATENATE(MONTH(E73),"/",YEAR(E73)),"") -> 7/2024 | G73: 38.67 | H73: =IF(I73,G73,0) -> 38.67 | I73: 45475
A74: Élio Squena - Tordilho Negro | B74: Loja | C74: Fornecedor | D74: Investimento | E74: 45477 | F74: =IF($E74,CONCATENATE(MONTH(E74),"/",YEAR(E74)),"") -> 7/2024 | G74: 615.88 | H74: =IF(I74,G74,0) -> 615.88 | I74: 45477
A75: Financiamento Creditas | C75: Dívida | D75: Dívida | E75: 45480 | F75: =IF($E75,CONCATENATE(MONTH(E75),"/",YEAR(E75)),"") -> 7/2024 | G75: 1231.13 | H75: =IF(I75,G75,0) -> 1231.13 | I75: 45480
A76: Qualitchê | C76: Fornecedor | D76: Investimento | E76: 45481 | F76: =IF($E76,CONCATENATE(MONTH(E76),"/",YEAR(E76)),"") -> 7/2024 | G76: 881.2 | H76: =IF(I76,G76,0) -> 881.2 | I76: 45481
A77: CC Nubank | B77: Vinicius | C77: Dívida | D77: Investimento | E77: 45481 | F77: =IF($E77,CONCATENATE(MONTH(E77),"/",YEAR(E77)),"") -> 7/2024 | G77: 1868.06 | H77: =IF(I77,G77,0) -> 1868.06 | I77: 45481
A78: Sanepar | B78: Casa | C78: Variavel | D78: Água | E78: 45481 | F78: =IF($E78,CONCATENATE(MONTH(E78),"/",YEAR(E78)),"") -> 7/2024 | G78: 56.66 | H78: =IF(I78,G78,0) -> 56.66 | I78: 45481
A79: Ademicon | B79: Casa | C79: Dívida | D79: Investimento | E79: 45481 | F79: =IF($E79,CONCATENATE(MONTH(E79),"/",YEAR(E79)),"") -> 7/2024 | G79: 666.95 | H79: =IF(I79,G79,0) -> 666.95 | I79: 45481
A80: Aluguel | C80: Variavel | D80: Locação | E80: 45483 | F80: =IF($E80,CONCATENATE(MONTH(E80),"/",YEAR(E80)),"") -> 7/2024 | G80: 1200 | H80: =IF(I80,G80,0) -> 1200 | I80: 45483
A81: Meganet | C81: Variavel | D81: Internet | E81: 45483 | F81: =IF($E81,CONCATENATE(MONTH(E81),"/",YEAR(E81)),"") -> 7/2024 | G81: 129.9 | H81: =IF(I81,G81,0) -> 129.9 | I81: 45483
A82: Meganet | C82: Variavel | D82: Internet | E82: 45483 | F82: =IF($E82,CONCATENATE(MONTH(E82),"/",YEAR(E82)),"") -> 7/2024 | G82: 99.9 | H82: =IF(I82,G82,0) -> 99.9 | I82: 45483
A83: Sanepar | B83: Loja | C83: Variavel | D83: Água | E83: 45483 | F83: =IF($E83,CONCATENATE(MONTH(E83),"/",YEAR(E83)),"") -> 7/2024 | G83: 97.24 | H83: =IF(I83,G83,0) -> 97.24 | I83: 45483
A84: CC Santander | C84: Dívida | D84: Investimento | E84: 45483 | F84: =IF($E84,CONCATENATE(MONTH(E84),"/",YEAR(E84)),"") -> 7/2024 | G84: 10560.96 | H84: =IF(I84,G84,0) -> 10560.96 | I84: 45483
A85: Copel | C85: Variavel | D85: Luz | E85: 45483 | F85: =IF($E85,CONCATENATE(MONTH(E85),"/",YEAR(E85)),"") -> 7/2024 | G85: 164.75 | H85: =IF(I85,G85,0) -> 164.75 | I85: 45483
A86: TIM | C86: Variavel | D86: Telefonia | E86: 45483 | F86: =IF($E86,CONCATENATE(MONTH(E86),"/",YEAR(E86)),"") -> 7/2024 | G86: 96.99 | H86: =IF(I86,G86,0) -> 96.99 | I86: 45483
A87: TIM | C87: Variavel | D87: Telefonia | E87: 45483 | F87: =IF($E87,CONCATENATE(MONTH(E87),"/",YEAR(E87)),"") -> 7/2024 | G87: 49.99 | H87: =IF(I87,G87,0) -> 49.99 | I87: 45483
A88: CC Cresol | C88: Dívida | D88: Investimento | E88: 45484 | F88: =IF($E88,CONCATENATE(MONTH(E88),"/",YEAR(E88)),"") -> 7/2024 | G88: 59.54 | H88: =IF(I88,G88,0) -> 59.54 | I88: 45484
A89: Pampasul | C89: Fornecedor | D89: Investimento | E89: 45488 | F89: =IF($E89,CONCATENATE(MONTH(E89),"/",YEAR(E89)),"") -> 7/2024 | G89: 932.26 | H89: =IF(I89,G89,0) -> 932.26 | I89: 45488
A90: Empréstimo Cresol | C90: Dívida | D90: Dívida | E90: 45488 | F90: =IF($E90,CONCATENATE(MONTH(E90),"/",YEAR(E90)),"") -> 7/2024 | G90: 1015.63 | H90: =IF(I90,G90,0) -> 1015.63 | I90: 45488
A91: MEI | B91: GIS | C91: Variavel | D91: Imposto | E91: 45493 | F91: =IF($E91,CONCATENATE(MONTH(E91),"/",YEAR(E91)),"") -> 7/2024 | G91: 71.6 | H91: =IF(I91,G91,0) -> 71.6 | I91: 45493
A92: CC Nubank | B92: Gislaine | C92: Dívida | D92: Investimento | E92: 45497 | F92: =IF($E92,CONCATENATE(MONTH(E92),"/",YEAR(E92)),"") -> 7/2024 | G92: 57.99 | H92: =IF(I92,G92,0) -> 57.99 | I92: 45497
A93: Copel | C93: Variavel | D93: Luz | E93: 45506 | F93: =IF($E93,CONCATENATE(MONTH(E93),"/",YEAR(E93)),"") -> 8/2024 | G93: 38.67 | H93: =IF(I93,G93,0) -> 38.67 | I93: 45506
A94: Financiamento Creditas | C94: Dívida | D94: Dívida | E94: 45511 | F94: =IF($E94,CONCATENATE(MONTH(E94),"/",YEAR(E94)),"") -> 8/2024 | G94: 1231.13 | H94: =IF(I94,G94,0) -> 1231.13 | I94: 45511
A95: CC Nubank | B95: Vinicius | C95: Dívida | D95: Investimento | E95: 45512 | F95: =IF($E95,CONCATENATE(MONTH(E95),"/",YEAR(E95)),"") -> 8/2024 | G95: 688.7 | H95: =IF(I95,G95,0) -> 688.7 | I95: 45512
A96: Sanepar | B96: Casa | C96: Variavel | D96: Água | E96: 45512 | F96: =IF($E96,CONCATENATE(MONTH(E96),"/",YEAR(E96)),"") -> 8/2024 | G96: 50.42 | H96: =IF(I96,G96,0) -> 50.42 | I96: 45512
A97: Ademicon | B97: Casa | C97: Dívida | D97: Investimento | E97: 45512 | F97: =IF($E97,CONCATENATE(MONTH(E97),"/",YEAR(E97)),"") -> 8/2024 | G97: 666.95 | H97: =IF(I97,G97,0) -> 666.95 | I97: 45512
A98: Aluguel | C98: Variavel | D98: Locação | E98: 45514 | F98: =IF($E98,CONCATENATE(MONTH(E98),"/",YEAR(E98)),"") -> 8/2024 | G98: 1200 | H98: =IF(I98,G98,0) -> 1200 | I98: 45514
A99: Meganet | C99: Variavel | D99: Internet | E99: 45514 | F99: =IF($E99,CONCATENATE(MONTH(E99),"/",YEAR(E99)),"") -> 8/2024 | G99: 129.9 | H99: =IF(I99,G99,0) -> 129.9 | I99: 45514
A100: Meganet | C100: Variavel | D100: Internet | E100: 45514 | F100: =IF($E100,CONCATENATE(MONTH(E100),"/",YEAR(E100)),"") -> 8/2024 | G100: 99.9 | H100: =IF(I100,G100,0) -> 99.9 | I100: 45514
A101: Sanepar | B101: Loja | C101: Variavel | D101: Água | E101: 45514 | F101: =IF($E101,CONCATENATE(MONTH(E101),"/",YEAR(E101)),"") -> 8/2024 | G101: 97.24 | H101: =IF(I101,G101,0) -> 97.24 | I101: 45514
A102: Copel | C102: Variavel | D102: Luz | E102: 45514 | F102: =IF($E102,CONCATENATE(MONTH(E102),"/",YEAR(E102)),"") -> 8/2024 | G102: 167 | H102: =IF(I102,G102,0) -> 167 | I102: 45514
A103: TIM | C103: Variavel | D103: Telefonia | E103: 45514 | F103: =IF($E103,CONCATENATE(MONTH(E103),"/",YEAR(E103)),"") -> 8/2024 | G103: 96.99 | H103: =IF(I103,G103,0) -> 96.99 | I103: 45514
A104: TIM | C104: Variavel | D104: Telefonia | E104: 45514 | F104: =IF($E104,CONCATENATE(MONTH(E104),"/",YEAR(E104)),"") -> 8/2024 | G104: 46.99 | H104: =IF(I104,G104,0) -> 46.99 | I104: 45514
A105: CC Cresol | C105: Dívida | D105: Investimento | E105: 45515 | F105: =IF($E105,CONCATENATE(MONTH(E105),"/",YEAR(E105)),"") -> 8/2024 | G105: 120.18 | H105: =IF(I105,G105,0) -> 120.18 | I105: 45515
A106: Seguro Kwid | C106: Variavel | D106: Seguro | E106: 45516 | F106: =IF($E106,CONCATENATE(MONTH(E106),"/",YEAR(E106)),"") -> 8/2024 | G106: 285.96 | H106: =IF(I106,G106,0) -> 285.96 | I106: 45516
A107: MOR | C107: Fornecedor | D107: Investimento | E107: 45518 | F107: =IF($E107,CONCATENATE(MONTH(E107),"/",YEAR(E107)),"") -> 8/2024 | G107: 716.27 | H107: =IF(I107,G107,0) -> 716.27 | I107: 45518
A108: Empréstimo Cresol | C108: Dívida | D108: Dívida | E108: 45519 | F108: =IF($E108,CONCATENATE(MONTH(E108),"/",YEAR(E108)),"") -> 8/2024 | G108: 1015.63 | H108: =IF(I108,G108,0) -> 1015.63 | I108: 45519
A109: MEI | B109: GIS | C109: Variavel | D109: Imposto | E109: 45524 | F109: =IF($E109,CONCATENATE(MONTH(E109),"/",YEAR(E109)),"") -> 8/2024 | G109: 71.6 | H109: =IF(I109,G109,0) -> 71.6 | I109: 45524
A110: Black Erva | C110: Fornecedor | D110: Investimento | E110: 45524 | F110: =IF($E110,CONCATENATE(MONTH(E110),"/",YEAR(E110)),"") -> 8/2024 | G110: 716.92 | H110: =IF(I110,G110,0) -> 716.92 | I110: 45524
A111: CC Nubank | B111: Gislaine | C111: Dívida | D111: Investimento | E111: 45528 | F111: =IF($E111,CONCATENATE(MONTH(E111),"/",YEAR(E111)),"") -> 8/2024 | G111: 55.83 | H111: =IF(I111,G111,0) -> 55.83 | I111: 45528
A112: CC Santander | C112: Dívida | D112: Investimento | E112: 45529 | F112: =IF($E112,CONCATENATE(MONTH(E112),"/",YEAR(E112)),"") -> 8/2024 | G112: 12082.98 | H112: =IF(I112,G112,0) -> 12082.98 | I112: 45514
A113: Mazutti | C113: Fornecedor | D113: Investimento | E113: 45530 | F113: =IF($E113,CONCATENATE(MONTH(E113),"/",YEAR(E113)),"") -> 8/2024 | G113: 390 | H113: =IF(I113,G113,0) -> 390 | I113: 45530
A114: Pé na Estrada | C114: Fornecedor | D114: Investimento | E114: 45533 | F114: =IF($E114,CONCATENATE(MONTH(E114),"/",YEAR(E114)),"") -> 8/2024 | G114: 1148.3 | H114: =IF(I114,G114,0) -> 1148.3 | I114: 45533
A115: C. F. Menezes & Carvalho Ltda - Qualitche | C115: Fornecedor | D115: Investimento | E115: 45536 | F115: =IF($E115,CONCATENATE(MONTH(E115),"/",YEAR(E115)),"") -> 9/2024 | G115: 614 | H115: 614 | I115: 45536
A116: Copel | C116: Variavel | D116: Luz | E116: 45537 | F116: =IF($E116,CONCATENATE(MONTH(E116),"/",YEAR(E116)),"") -> 9/2024 | G116: 38.67 | H116: =IF(I116,G116,0) -> 38.67 | I116: 45537
A117: Financiamento Creditas | C117: Dívida | D117: Dívida | E117: 45542 | F117: =IF($E117,CONCATENATE(MONTH(E117),"/",YEAR(E117)),"") -> 9/2024 | G117: 1231.13 | H117: =IF(I117,G117,0) -> 1231.13 | I117: 45542
A118: CC Nubank | B118: Vinicius | C118: Dívida | D118: Investimento | E118: 45543 | F118: =IF($E118,CONCATENATE(MONTH(E118),"/",YEAR(E118)),"") -> 9/2024 | G118: 688.7 | H118: =IF(I118,G118,0) -> 688.7 | I118: 45543
A119: Sanepar | B119: Casa | C119: Variavel | D119: Água | E119: 45543 | F119: =IF($E119,CONCATENATE(MONTH(E119),"/",YEAR(E119)),"") -> 9/2024 | G119: 53.54 | H119: =IF(I119,G119,0) -> 53.54 | I119: 45543
A120: Ademicon | B120: Casa | C120: Dívida | D120: Investimento | E120: 45543 | F120: =IF($E120,CONCATENATE(MONTH(E120),"/",YEAR(E120)),"") -> 9/2024 | G120: 666.95 | H120: =IF(I120,G120,0) -> 666.95 | I120: 45543
A121: Aluguel | C121: Variavel | D121: Locação | E121: 45545 | F121: =IF($E121,CONCATENATE(MONTH(E121),"/",YEAR(E121)),"") -> 9/2024 | G121: 1200 | H121: =IF(I121,G121,0) -> 1200 | I121: 45545
A122: Meganet | C122: Variavel | D122: Internet | E122: 45545 | F122: =IF($E122,CONCATENATE(MONTH(E122),"/",YEAR(E122)),"") -> 9/2024 | G122: 129.9 | H122: =IF(I122,G122,0) -> 129.9 | I122: 45545
A123: Meganet | C123: Variavel | D123: Internet | E123: 45545 | F123: =IF($E123,CONCATENATE(MONTH(E123),"/",YEAR(E123)),"") -> 9/2024 | G123: 99.9 | H123: =IF(I123,G123,0) -> 99.9 | I123: 45545
A124: Sanepar | B124: Loja | C124: Variavel | D124: Água | E124: 45545 | F124: =IF($E124,CONCATENATE(MONTH(E124),"/",YEAR(E124)),"") -> 9/2024 | G124: 97.24 | H124: =IF(I124,G124,0) -> 97.24 | I124: 45545
A125: Seguro Kwid | C125: Variavel | D125: Seguro | E125: 45545 | F125: =IF($E125,CONCATENATE(MONTH(E125),"/",YEAR(E125)),"") -> 9/2024 | G125: 285.96 | H125: =IF(I125,G125,0) -> 285.96 | I125: 45545
A126: Copel | C126: Variavel | D126: Luz | E126: 45545 | F126: =IF($E126,CONCATENATE(MONTH(E126),"/",YEAR(E126)),"") -> 9/2024 | G126: 181.16 | H126: =IF(I126,G126,0) -> 181.16 | I126: 45545
A127: TIM | C127: Variavel | D127: Telefonia | E127: 45545 | F127: =IF($E127,CONCATENATE(MONTH(E127),"/",YEAR(E127)),"") -> 9/2024 | G127: 96.99 | H127: =IF(I127,G127,0) -> 96.99 | I127: 45545
A128: TIM | C128: Variavel | D128: Telefonia | E128: 45545 | F128: =IF($E128,CONCATENATE(MONTH(E128),"/",YEAR(E128)),"") -> 9/2024 | G128: 49.99 | H128: =IF(I128,G128,0) -> 49.99 | I128: 45545
A129: CC Cresol | C129: Dívida | D129: Investimento | E129: 45546 | F129: =IF($E129,CONCATENATE(MONTH(E129),"/",YEAR(E129)),"") -> 9/2024 | G129: 62.6 | H129: =IF(I129,G129,0) -> 62.6 | I129: 45546
A130: Pampasul | C130: Fornecedor | D130: Investimento | E130: 45547 | F130: =IF($E130,CONCATENATE(MONTH(E130),"/",YEAR(E130)),"") -> 9/2024 | G130: 592.25 | H130: =IF(I130,G130,0) -> 592.25 | I130: 45547
...

Sheet Custo marcas
A1: Sacudido's | B1: =IFERROR(__xludf.DUMMYFUNCTION("IMPORTRANGE(""https://docs.google.com/spreadsheets/d/1v7LYSfrIwyA0rrnvpZP1xdP32gJSacmF2axgu2Ii5X8/edit?gid=1175560505#gid=1175560505"", ""'Inventário de Estoque'!L1:L1"")"),"#REF!") -> #REF! | C1: =B1*2 -> #REF!
A2: Pé na estrada | B2: =IFERROR(__xludf.DUMMYFUNCTION("IMPORTRANGE(""https://docs.google.com/spreadsheets/d/1uN_smXhDQT14ctPzciDbxqtaVORBXQaa6NUJzIEWpkQ/edit?gid=1549833940#gid=1549833940"", ""'Inventário de Estoque'!L1:L1"")"),"#REF!") -> #REF! | C2: =B2*2 -> #REF!
A3: Kappell | B3: =IFERROR(__xludf.DUMMYFUNCTION("IMPORTRANGE(""https://docs.google.com/spreadsheets/d/14YKVMFWnonTFFbLI75yjFymR53okEYkIzGcO5nS5LAc/edit?gid=361854317#gid=361854317"", ""'Inventário de Estoque'!L1:L1"")"),"#REF!") -> #REF! | C3: =B3*2 -> #REF!
A4: Vuollo | B4: =IFERROR(__xludf.DUMMYFUNCTION("IMPORTRANGE(""https://docs.google.com/spreadsheets/d/1pmhD74GsPoEZa3BZjLOMYJCrvJ2C5C-973gDnuBLH38/edit?gid=1758114367#gid=1758114367"", ""'Inventário de Estoque'!L1:L1"")"),"#REF!") -> #REF! | C4: =B4*2 -> #REF!
A5: Cla-cle | B5: =IFERROR(__xludf.DUMMYFUNCTION("IMPORTRANGE(""https://docs.google.com/spreadsheets/d/1N4I4KPDNkpitO0xZkJy6QHL0g37U0pnjLh8cLhUBDCI/edit?gid=542127081#gid=542127081"", ""'Inventário de Estoque'!L1:L1"")"),"#REF!") -> #REF! | C5: =B5*2 -> #REF!
A6: Qualitche | B6: =IFERROR(__xludf.DUMMYFUNCTION("IMPORTRANGE(""https://docs.google.com/spreadsheets/d/1JzQUhonU7d5R2Bilb2wA3sQmgwsx4I8ooBONFTWXf5w/edit?gid=1912606609#gid=1912606609"", ""'Inventário de Estoque'!L1:L1"")"),"#REF!") -> #REF! | C6: =B6*2 -> #REF!
A7: Pura Raça | B7: =IFERROR(__xludf.DUMMYFUNCTION("IMPORTRANGE(""https://docs.google.com/spreadsheets/d/11tYWoSGCdybRgk8GnZXXdtK4ZyQgLqzQskHtbsRJo6o/edit?gid=438354460#gid=438354460"", ""'Inventário de Estoque'!L1:L1"")"),"#REF!") -> #REF! | C7: =B7*2 -> #REF!
A8: Texanus | B8: =IFERROR(__xludf.DUMMYFUNCTION("IMPORTRANGE(""https://docs.google.com/spreadsheets/d/1odqGiEiMPrDWQr7T-scvjbEUjGIaOzTLkTwiIstwuiQ/edit?gid=1559247720#gid=1559247720"", ""'Inventário de Estoque'!L1:L1"")"),"#REF!") -> #REF! | C8: =B8*2 -> #REF!
A9: Mula Rosa | B9: =IFERROR(__xludf.DUMMYFUNCTION("IMPORTRANGE(""https://docs.google.com/spreadsheets/d/174b3LO_c3aR-IS8A91CUJ91S4FGemVHoCWLRm6SrHCA/edit?gid=710208362#gid=710208362"", ""'Inventário de Estoque'!L1:L1"")"),"#REF!") -> #REF! | C9: =B9*2 -> #REF!
A10: Montana | B10: =IFERROR(__xludf.DUMMYFUNCTION("IMPORTRANGE(""https://docs.google.com/spreadsheets/d/19S80tP4e7P3RV7SnlzRsH4UArEa_W3Od4gNSTdQ2588/edit?gid=1141953125#gid=1141953125"", ""'Inventário de Estoque'!L1:L1"")"),"#REF!") -> #REF! | C10: =B10*2 -> #REF!
A11: Cowgirl | B11: =IFERROR(__xludf.DUMMYFUNCTION("IMPORTRANGE(""https://docs.google.com/spreadsheets/d/1KS-VNuujap8DkmofjUzSTISnc0w5ibmXSZcCp-9bVnM/edit?gid=840031567#gid=840031567"", ""'Inventário de Estoque'!L1:L1"")"),"#REF!") -> #REF! | C11: =B11*2 -> #REF!
A12: Pampa Sul | B12: =IFERROR(__xludf.DUMMYFUNCTION("IMPORTRANGE(""https://docs.google.com/spreadsheets/d/1cUmN9IpPQGidGW1nT26FqsPC6lhljQ4IQoWxN1JYb-M/edit?gid=1485932453#gid=1485932453"", ""'Inventário de Estoque'!L1:L1"")"),"#REF!") -> #REF! | C12: =B12*2 -> #REF!
A13: Made in Mato | B13: =IFERROR(__xludf.DUMMYFUNCTION("IMPORTRANGE(""https://docs.google.com/spreadsheets/d/1tQ_GjBt1INNPF4y9dzUtDUQzkToDyIRhe7xW643Lg4U/edit?gid=522286354#gid=522286354"", ""'Inventário de Estoque'!L1:L1"")"),"#REF!") -> #REF! | C13: =B13*2 -> #REF!
A14: Master Couros | B14: =IFERROR(__xludf.DUMMYFUNCTION("IMPORTRANGE(""https://docs.google.com/spreadsheets/d/1NpM0m06KsngqrSI2pwuxFYdXNW5e9CHK3qo5zEe1Orw/edit?gid=1822251035#gid=1822251035"", ""'Inventário de Estoque'!L1:L1"")"),"#REF!") -> #REF! | C14: =B14*2 -> #REF!
A15: Ciarin | B15: =IFERROR(__xludf.DUMMYFUNCTION("IMPORTRANGE(""https://docs.google.com/spreadsheets/d/1H6tg39SrJY6glzjKJBhoEb9Qiby_AbRZ8VDk4dKiTwk/edit?gid=1190618551#gid=1190618551"", ""'Inventário de Estoque'!L1:L1"")"),"#REF!") -> #REF! | C15: =B15*2 -> #REF!
A16: Selaria Pinheiro | B16: =IFERROR(__xludf.DUMMYFUNCTION("IMPORTRANGE(""https://docs.google.com/spreadsheets/d/19zsLB6iRpAYilIVvaCoY4rghGNkx2P0LWbIrFfj5G5s/edit?gid=2043833364#gid=2043833364"", ""'Inventário de Estoque'!L1:L1"")"),"#REF!") -> #REF! | C16: =B16*2 -> #REF!
A17: Texas Farm | B17: =IFERROR(__xludf.DUMMYFUNCTION("IMPORTRANGE(""https://docs.google.com/spreadsheets/d/1ARsi6fbFT7P7rTCA6JfXQtcgJz5ItrMQoL9F9BR0L94/edit?gid=1532243408#gid=1532243408"", ""'Inventário de Estoque'!L1:L1"")"),"#REF!") -> #REF! | C17: =B17*2 -> #REF!
A18: Tordilho Negro | B18: =IFERROR(__xludf.DUMMYFUNCTION("IMPORTRANGE(""https://docs.google.com/spreadsheets/d/1URh45kCKLaAU0VNzdVEgjCHQRWCLmQ63ZaMuigU-vbI/edit?gid=681508335#gid=681508335"", ""'Inventário de Estoque'!L1:L1"")"),"#REF!") -> #REF! | C18: =B18*2 -> #REF!
A19: MOR | B19: =IFERROR(__xludf.DUMMYFUNCTION("IMPORTRANGE(""https://docs.google.com/spreadsheets/d/1NnlqBRsE-LBQKiHRCojuwoIGdfy6Vg5ECoqmWRzE95k/edit?gid=1106525878#gid=1106525878"", ""'Inventário de Estoque'!L1:L1"")"),"#REF!") -> #REF! | C19: =B19*2 -> #REF!
A20: Black | B20: =IFERROR(__xludf.DUMMYFUNCTION("IMPORTRANGE(""https://docs.google.com/spreadsheets/d/1VJqyIHZS1_V2zxoXXclSXb5haVQZbgWH_qVNkpA1SAY/edit?gid=1736627674#gid=1736627674"", ""'Inventário de Estoque'!L1:L1"")"),"#REF!") -> #REF! | C20: =B20*2 -> #REF!
B25: =SUM(B1:B24) -> #REF! | C25: =SUM(C1:C24) -> #REF!

Sheet Categorias
A1: Categorias de conta
A2: Selecione
A3: Dívida
A4: Luz
A5: Água
A6: Investimento
A7: Locação
A8: Telefonia
A9: Internet
A10: Imposto
A11: Seguro
A12: Combustivel
A13: Mercado

Sheet Calculadora de preço
A1: Valor do Produto | B1: 219 | D1: Tabela de tarifas Stone | F1: Parcela | G1: Á Receber | H1: Margem
A2: Valor Sugerido de venda | B2: =(($B$1*$B$3)) -> 438 | D2: Antecipação | E2: 2.6 | F2: - | G2: -
A3: Markup | B3: 2 | D3: Débito | E3: 1.81 | F3: =B2-(B2*(E3/100)) -> 430.0722 | G3: =$B$2-($B$2*($E3/100)) -> 430.0722 | H3: =$G3-$B$1 -> 211.0722 | M3: Projeção | N3: A vista | P3: A Prazo | Q3: Estoque | S3: Parcelas | T3: Valor | U3: A Prazo
A4: Margem de lucro | B4: =(($B$2-$B$1)/$B$2) -> 0.5 | D4: Crédito | E4: 2.87 | F4: =B2-(B2*(E4/100))-(B2*(E2/100)) -> 414.0414 | G4: =$B$2-($B$2*(($E4+$E$2)/100)) -> 414.0414 | H4: =$G4-$B$1 -> 195.0414 | J4: 89 | K4: 179.9 | L4: Blusa Sul de Minas | M4: =((($J4*$B$4)+($J4*#REF!))*100)/(100-$B$5) -> #REF! | N4: 135.9 | O4: =(N4*100)/K4 -> 75.541968 | P4: 149.9 | Q4: 24 | R4: =Q4*N4 -> 3261.6 | S4: 6 | T4: =(N4*1.2)/S4 -> 27.18 | U4: =S4*T4 -> 163.08
A5: Tarifa máxima | B5: 12.14 | D5: 2a 6x | E5: 3.34 | G5: =B2-((E5/100)*B2) -> 423.3708 | H5: =$G5-$B$1 -> 204.3708 | J5: 69 | K5: 169.9 | L5: Moletom Bem Campeiro - Infantil | M5: =((($J5*$B$4)+($J5*#REF!))*100)/(100-$B$5) -> #REF! | N5: 105.9 | O5: =(N5*100)/K5 -> 62.330783 | P5: 119.9 | Q5: 14 | R5: =Q5*N5 -> 1482.6 | S5: 6 | T5: =(N5*1.2)/S5 -> 21.18 | U5: =S5*T5 -> 127.08
D6: 2 | F6: =$G$5/$D6 -> 211.6854 | G6: =($F6-($F6*((1*$E$2)/100)))+($F6-($F6*((2*$E$2)/100))) -> 406.85934 | H6: =$G6-$B$1 -> 187.85934 | J6: 89 | K6: 209.9 | L6: Moletom Bem Campeiro - Adulto | M6: =((($J6*$B$4)+($J6*#REF!))*100)/(100-$B$5) -> #REF! | N6: 135.9 | O6: =(N6*100)/K6 -> 64.745117 | P6: 149.9 | Q6: 25 | R6: =Q6*N6 -> 3397.5 | S6: 6 | T6: =(N6*1.2)/S6 -> 27.18 | U6: =S6*T6 -> 163.08
D7: 3 | F7: =$G$5/$D7 -> 141.1236 | G7: =($F7-($F7*((1*$E$2)/100)))+($F7-($F7*((2*$E$2)/100)))+($F7-($F7*((3*$E$2)/100))) -> 401.35552 | H7: =$G7-$B$1 -> 182.35552 | J7: 116.5 | K7: 239.9 | L7: Moletom Cowgirl | M7: =((($J7*$B$4)+($J7*#REF!))*100)/(100-$B$5) -> #REF! | N7: 175.9 | O7: =(N7*100)/K7 -> 73.322218 | P7: 195.9 | Q7: 8 | R7: =Q7*N7 -> 1407.2 | S7: 6 | T7: =(N7*1.2)/S7 -> 35.18 | U7: =S7*T7 -> 211.08
D8: 4 | F8: =$G$5/$D8 -> 105.8427 | G8: =($F8-($F8*((1*$E$2)/100)))+($F8-($F8*((2*$E$2)/100)))+($F8-($F8*((3*$E$2)/100)))+($F8-($F8*((4*$E$2)/100))) -> 395.8517 | H8: =$G8-$B$1 -> 176.8517 | J8: 36 | K8: 79.9 | L8: Corta Vento - Eklética | M8: =((($J8*$B$4)+($J8*#REF!))*100)/(100-$B$5) -> #REF! | N8: 59.9 | O8: =(N8*100)/K8 -> 74.968711 | P8: 65.9 | Q8: 26 | R8: =Q8*N8 -> 1557.4 | S8: 6 | T8: =(N8*1.2)/S8 -> 11.98 | U8: =S8*T8 -> 71.88
D9: 5 | F9: =$G$5/$D9 -> 84.67416 | G9: =($F9-($F9*((1*$E$2)/100)))+($F9-($F9*((2*$E$2)/100)))+($F9-($F9*((3*$E$2)/100)))+($F9-($F9*((4*$E$2)/100)))+($F9-($F9*((5*$E$2)/100))) -> 390.34788 | H9: =$G9-$B$1 -> 171.34788 | J9: 54 | K9: 129.9 | L9: Manga Longa Bem Campeiro - Adulto | M9: =((($J9*$B$4)+($J9*#REF!))*100)/(100-$B$5) -> #REF! | N9: 85.9 | O9: =(N9*100)/K9 -> 66.127791 | P9: 95.9 | Q9: 28 | R9: =Q9*N9 -> 2405.2 | S9: 6 | T9: =(N9*1.2)/S9 -> 17.18 | U9: =S9*T9 -> 103.08
D10: 6 | F10: =$G$5/$D10 -> 70.5618 | G10: =($F10-($F10*((1*$E$2)/100)))+($F10-($F10*((2*$E$2)/100)))+($F10-($F10*((3*$E$2)/100)))+($F10-($F10*((4*$E$2)/100)))+($F10-($F10*((5*$E$2)/100)))+($F10-($F10*((6*$E$2)/100))) -> 384.84406 | H10: =$G10-$B$1 -> 165.84406 | J10: 44 | K10: 109.9 | L10: Manga Longa Bem Campeiro - Infantil | M10: =((($J10*$B$4)+($J10*#REF!))*100)/(100-$B$5) -> #REF! | N10: 69.9 | O10: =(N10*100)/K10 -> 63.603276 | P10: 79.9 | Q10: 18 | R10: =Q10*N10 -> 1258.2 | S10: 6 | T10: =(N10*1.2)/S10 -> 13.98 | U10: =S10*T10 -> 83.88
D11: Pix | E11: 0 | G11: =$B$2-($B$2*($E11/100)) -> 438 | H11: =$G11-$B$1 -> 219 | J11: 39.77 | K11: 99.9 | L11: Manga Longa - Country Kids - Infantil | M11: =((($J11*$B$4)+($J11*#REF!))*100)/(100-$B$5) -> #REF! | N11: 69.9 | O11: =(N11*100)/K11 -> 69.96997 | P11: 79.9 | Q11: 13 | R11: =Q11*N11 -> 908.7 | S11: 6 | T11: =(N11*1.2)/S11 -> 13.98 | U11: =S11*T11 -> 83.88
D12: Dinheiro | E12: 0 | G12: =$B$2-($B$2*($E12/100)) -> 438 | H12: =$G12-$B$1 -> 219 | J12: 43.48 | K12: 109.9 | L12: Manga Longa - Jopper Bulls - Adulto | M12: =((($J12*$B$4)+($J12*#REF!))*100)/(100-$B$5) -> #REF! | N12: 85.9 | O12: =(N12*100)/K12 -> 78.161965 | P12: 95.9 | Q12: 12 | R12: =Q12*N12 -> 1030.8 | S12: 6 | T12: =(N12*1.2)/S12 -> 17.18 | U12: =S12*T12 -> 103.08
J13: 43.48 | K13: 109.9 | L13: Manga Longa - Mula Rosa - Adulto | M13: =((($J13*$B$4)+($J13*#REF!))*100)/(100-$B$5) -> #REF! | N13: 85.9 | O13: =(N13*100)/K13 -> 78.161965 | P13: 95.9 | Q13: 13 | R13: =Q13*N13 -> 1116.7 | S13: 6 | T13: =(N13*1.2)/S13 -> 17.18 | U13: =S13*T13 -> 103.08
R15: =SUM(R4:R13) -> 17825.9

Sheet Tordilho Negro
A1: Produto | B1: Recebido | C1: Atual | D1: Custo | E1: Venda | F1: 45352 | H1: 45383 | J1: 45413 | L1: 45444 | N1: 45474 | P1: 45505 | R1: 45536 | T1: 45566 | V1: 45597 | X1: 45627
A2: Camisa Polo Adulto | B2: =8+11+14+13+4+11+2+3+7+10+16+13+3+8+10+5+8+12+17+13+13+17+12+9+6+10+5+9+13+18+11+10+9+15+6+6+11+17+13+10 -> 408 | C2: 383 | D2: 39.72 | E2: 89.9 | F2: 1 | G2: =F2*D2 -> 39.72 | H2: 10 | I2: =H2*D2 -> 397.2 | J2: 4 | K2: =J2*D2 -> 158.88 | L2: 9 | M2: =L2*D2 -> 357.48 | O2: =N2*D2 -> 0 | Q2: =P2*F2 -> 0 | S2: =R2*H2 -> 0 | U2: =T2*J2 -> 0 | W2: =V2*L2 -> 0 | Y2: =X2*N2 -> 0
A3: Camisa Polo Baby | B3: =3+4+2+5+5+4 -> 23 | C3: 22 | D3: 25.03 | E3: 59.9 | F3: 1 | G3: =F3*D3 -> 25.03 | I3: =H3*D3 -> 0 | K3: =J3*D3 -> 0 | M3: =L3*D3 -> 0 | O3: =N3*D3 -> 0 | Q3: =P3*F3 -> 0 | S3: =R3*H3 -> 0 | U3: =T3*J3 -> 0 | W3: =V3*L3 -> 0 | Y3: =X3*N3 -> 0
A4: Camisa Polo Infantil | B4: =4+5+5+3+4+3+4+5+4 -> 37 | C4: 32 | D4: 29.08 | E4: 69.9 | F4: 1 | G4: =F4*D4 -> 29.08 | H4: 2 | I4: =H4*D4 -> 58.16 | K4: =J4*D4 -> 0 | L4: 1 | M4: =L4*D4 -> 29.08 | O4: =N4*D4 -> 0 | Q4: =P4*F4 -> 0 | S4: =R4*H4 -> 0 | U4: =T4*J4 -> 0 | W4: =V4*L4 -> 0 | Y4: =X4*N4 -> 0
A5: Ceva Mate | B5: 213 | C5: 210 | D5: 4.55 | E5: 15 | F5: 3 | G5: =F5*D5 -> 13.65 | I5: =H5*D5 -> 0 | K5: =J5*D5 -> 0 | M5: =L5*D5 -> 0 | O5: =N5*D5 -> 0 | Q5: =P5*F5 -> 0 | S5: =R5*H5 -> 0 | U5: =T5*J5 -> 0 | W5: =V5*L5 -> 0 | Y5: =X5*N5 -> 0
A6: Chinelo Campeiro | B6: 26 | C6: 25 | D6: 34.74 | E6: 69.9 | G6: =F6*D6 -> 0 | H6: 1 | I6: =H6*D6 -> 34.74 | K6: =J6*D6 -> 0 | M6: =L6*D6 -> 0 | O6: =N6*D6 -> 0 | Q6: =P6*F6 -> 0 | S6: =R6*H6 -> 0 | U6: =T6*J6 -> 0 | W6: =V6*L6 -> 0 | Y6: =X6*N6 -> 0
A7: Cuia c/ Bomba | B7: 15 | C7: 10 | D7: 34.97 | E7: 69.9 | F7: 1 | G7: =F7*D7 -> 34.97 | H7: 3 | I7: =H7*D7 -> 104.91 | J7: 1 | K7: =J7*D7 -> 34.97 | M7: =L7*D7 -> 0 | O7: =N7*D7 -> 0 | Q7: =P7*F7 -> 0 | S7: =R7*H7 -> 0 | U7: =T7*J7 -> 0 | W7: =V7*L7 -> 0 | Y7: =X7*N7 -> 0
A8: Mateira | B8: 26 | C8: 26 | D8: 25 | E8: 79.9 | G8: =F8*D8 -> 0 | I8: =H8*D8 -> 0 | K8: =J8*D8 -> 0 | M8: =L8*D8 -> 0 | O8: =N8*D8 -> 0 | Q8: =P8*F8 -> 0 | S8: =R8*H8 -> 0 | U8: =T8*J8 -> 0 | W8: =V8*L8 -> 0 | Y8: =X8*N8 -> 0
B9: =SUM(B2:B8) -> 748 | C9: =SUM(C2:C8) -> 708 | F9: =SUM(F2:F8) -> 7 | G9: =SUM(G2:G8) -> 142.45 | H9: =SUM(H2:H8) -> 16 | I9: =SUM(I2:I8) -> 595.01 | J9: =SUM(J2:J8) -> 5 | K9: =SUM(K2:K8) -> 193.85 | L9: =SUM(L2:L8) -> 10 | M9: =SUM(M2:M8) -> 386.56 | ... Y9: =SUM(Y2:Y8) -> 0
C11: =(13+17+11+3+9+8+6+4+5+9+6+11+9+18+13+11+8+15+13)+(17+13+11+8+2+2+11+4+5+2+14+13+9+7+13+12+10+8) -> 350 | D11: =B2-B11 -> 408 | E11: =D11-C11 -> 58 | F11: =E11*D2 -> 2303.76
C12: =5+4+5+2+3+2 -> 21 | D12: =B3-B12 -> 23 | E12: =D12-C12 -> 2 | F12: =E12*D3 -> 50.06
C13: =2+4+3+2+3+4+2+3+4 -> 27 | D13: =B4-B13 -> 37 | E13: =D13-C13 -> 10 | F13: =E13*D4 -> 290.8
C14: =210 -> 210 | D14: =B5-B14 -> 213 | E14: =D14-C14 -> 3 | F14: =E14*D5 -> 13.65
C15: 23 | D15: =B6-B15 -> 26 | E15: =D15-C15 -> 3 | F15: =E15*D6 -> 104.22
C16: 6 | D16: =B7-B16 -> 15 | E16: =D16-C16 -> 9 | F16: =E16*D7 -> 314.73
C17: 23 | D17: =B8-B17 -> 26 | E17: =D17-C17 -> 3 | F17: =E17*D8 -> 75
F18: =SUM(F11:F17) -> 3152.22
A21: Pagamentos realizados
A22: 45624 | B22: 400
A23: 45476 | B23: 615.88
A24: 45419 | B24: 560.04
A25: 45385 | B25: 141.95
B30: =SUM(B22:B25) -> 1717.87 | C30: =F18-B30 -> 1434.35

Sheet Marilene
A2: Corta Vento | B2: 31 | C2: 26 | D2: 5
A3: Lenço

Sheet Sheet3
A1: Cuia c/ Bomba - Tordilho Negro | B1: 18/03/2024 | C1: 34.97 | F1: Corta Vento | G1: Preta | H1: 36 | I1: PAGO
A2: Ceva Mate - Tordilho Negro | B2: 18/03/2024 | C2: 4.55 | F2: Corta Vento | G2: Preta | H2: 36 | I2: PAGO
A3: Camisa Infantil Tordilho Negro Vermelho - 2 | B3: 20/03/2024 | C3: 29.08 | F3: Corta Vento | G3: Cinza | H3: 36 | I3: PAGO
A4: Camisa Masculina Tordilho Negro Vermelha - G | B4: 28/03/2024 | C4: 39.72 | F4: Corta Vento | G4: Preto | H4: 36 | I4: PAGO
A5: Camisa Infantil Tordilho Negro Verde - 4 | B5: 30/03/2024 | C5: 29.08 | F5: Corta Vento | G5: Verde | H5: 36 | I5: PAGO
A6: Ceva Mate - Tordilho Negro | B6: 30/03/2024 | C6: 4.55
C7: =SUM(C1:C6) -> 141.95 | D7: PAGO
J8: Camisa Polo Adulto | K8: 39.72 | M8: =220+188 -> 408 | N8: =M8*K8 -> 16205.76 | O8: 89.9 | Q8: 389 | R8: =M8-Q8 -> 19
A9: Camisa Masculina Tordilho Negro Branca - GG | C9: 39.72 | J9: Camisa Polo Baby | K9: 25.03 | M9: 23 | N9: =M9*K9 -> 575.69 | O9: 59.9 | Q9: 22 | R9: =M9-Q9 -> 1
A10: Camisa Masculina Tordilho Negro Preta - M | C10: 39.72 | G10: jan | H10: 50 | J10: Camisa Polo Infantil | K10: 29.08 | M10: 37 | N10: =M10*K10 -> 1075.96 | O10: 69.9 | Q10: 33 | R10: =M10-Q10 -> 4
A11: Cuia c/ Bomba - Tordilho Negro | C11: 34.97 | G11: dez | H11: 200 | J11: Ceva Mate | K11: 4.55 | M11: 213 | N11: =M11*K11 -> 969.15 | O11: 15 | Q11: 210 | R11: =M11-Q11 -> 3
A12: Camisa Feminina Tordilho Negro Vermelha - M | C12: 39.72 | G12: abr | H12: =72+50+36+72 -> 230 | J12: Chinelo Campeiro | K12: 34.97 | M12: 26 | N12: =M12*K12 -> 909.22 | O12: 69.9 | Q12: 25 | R12: =M12-Q12 -> 1
A13: Camisa Infantil Tordilho Negro Azul - 4 | C13: 29.08 | J13: Cuia c bomba | K13: 34.97 | M13: 15 | N13: =M13*K13 -> 524.55 | O13: 69.9 | Q13: 10 | R13: =M13-Q13 -> 5
A14: Camisa Feminina Tordilho Negro Azul - M | C14: 39.72 | J14: Mateira | K14: 59.1 | M14: 26 | N14: =M14*K14 -> 1536.6 | Q14: 26 | R14: =M14-Q14 -> 0
A15: Camisa Feminina Tordilho Negro Preta - GG | C15: 39.72
A16: Camisa Feminina Tordilho Negro Preta - M | C16: 39.72 | G16: =9*36 -> 324 | H16: 356 | I16: =SUM(G16:H16) -> 680 | N16: =SUM(N8:N14) -> 21796.93
A17: Camisa Infantil Tordilho Negro Vermelho - 4 | C17: 29.08
A18: Camisa Masculina Tordilho Negro Vermelha - M | C18: 39.72
A19: Camisa Feminina Tordilho Negro Vermelha - M | C19: 39.72
A20: Camisa Feminina Tordilho Negro Vermelha - G | C20: 39.72
A21: Camisa Feminina Tordilho Negro Preta - M | C21: 39.72
A22: Chinelo Campeiro - Tordilho Negro | C22: 34.74 | K22: Despesas Fixas | L22: 5000 | M22: =M26*0.25 -> 20.745 | P22: Antecipação | Q22: 1.8
A23: Cuia c/ Bomba - Tordilho Negro | C23: 34.97 | K23: Margem de lucro | M23: 2 | P23: Débito | Q23: 2.02
K24: Margem para cobrir cartão | M24: 0.06 | P24: Crédito | Q24: 3.68
C25: =SUM(C9:C24) -> 560.04 | D25: PAGO | H25: 14.9 | I25: 0.25 | J25: =H25*I25 -> 3.725 | P25: 2a 6x | Q25: 3.99 | R25: =Q25/100 -> 0.0399
K26: Custo do produto | M26: 82.98
A27: Camisa Feminina Tordilho Negro Branca - G | C27: 39.72 | K27: Preço Sugerido de venda | M27: =((M26*M23)+M22)+(((M26*M23)+M22)*M24) -> 197.9073
A28: Camisa Masculina Tordilho Negro Branca - M | C28: 39.72 | K28: Desconto | L28: 0
K29: Preço que receberemos no pagamento | M29: =M27-(M27*R25) -> 190.0108
M30: =M29-(M29*L28) -> 190.0108
E36: 500000 | F36: =E36+H37 -> 504428
F37: 0.008856 | G37: 50 | H37: =H38*G37 -> 4428 | O37: 19 | P37: 9 | Q37: =O37/P37 -> 2.1111111
G38: =F37/G37 -> 0.00017712 | H38: =E36*G38 -> 88.56 | O38: 4.5 | P38: 5 | Q38: =O38/P38 -> 0.9
Q39: 1
C40: =SUM(C27:C38) -> 79.44 | Q40: =SUM(Q37:Q39) -> 4.0111111
Q42: 4
Q43: 8
A49: Play 4 | B49: 1500
A50: Plaina desengrossadeira | B50: 1500
A51: Sofá com chaise 4 metros | B51: 1500
A52: Computador gamer | B52: 4000
A53: Monitor | B53: 750
B60: =SUM(B49:B59) -> 9250

Sheet Check TN
A1: Infantil | B1: G | D1: Atual | E1: 2 | G1: Atual | H1: 4 | J1: Atual | K1: 6 | M1: Atual | N1: 8 | P1: Atual
A2: VERDE | B2: 3 | C2: 2 | D2: =B2-C2 -> 1 | E2: 5 | F2: 5 | G2: =E2-F2 -> 0 | H2: 4 | I2: 2 | J2: =H2-I2 -> 2 | K2: 3 | L2: 3 | M2: =K2-L2 -> 0 | N2: 4 | O2: 4 | P2: =N2-O2 -> 0
A3: AZUL | B3: 4 | C3: 4 | D3: =B3-C3 -> 0 | E3: 5 | F3: 5 | G3: =E3-F3 -> 0 | H3: 5 | I3: 2 | J3: =H3-I3 -> 3 | K3: 4 | L3: 4 | M3: =K3-L3 -> 0 | N3: 5 | O3: 3 | P3: =N3-O3 -> 2
A4: VERMELHO | B4: 2 | C4: 2 | D4: =B4-C4 -> 0 | E4: 4 | F4: 3 | G4: =E4-F4 -> 1 | H4: 5 | I4: 2 | J4: =H4-I4 -> 3 | K4: 3 | L4: 3 | M4: =K4-L4 -> 0 | N4: 4 | O4: 4 | P4: =N4-O4 -> 0
A6: Feminina | B6: P | D6: Atual | E6: M | G6: Atual | H6: G | J6: Atual | K6: GG | M6: Atual
A7: VERMELHA | B7: 13 | C7: 13 | D7: =B7-C7 -> 0 | E7: 17 | F7: 15 | G7: =E7-F7 -> 2 | H7: 12 | I7: 11 | J7: =H7-I7 -> 1 | K7: 9 | L7: 8 | M7: =K7-L7 -> 1
A8: BRANCA | B8: 6 | C8: 6 | D8: =B8-C8 -> 0 | E8: 10 | F8: 8 | G8: =E8-F8 -> 2 | H8: 5 | I8: 3 | J8: =H8-I8 -> 2 | K8: 9 | L8: 9 | M8: =K8-L8 -> 0
A9: VERDE | B9: 13 | C9: 13 | D9: =B9-C9 -> 0 | E9: 18 | F9: 18 | G9: =E9-F9 -> 0 | H9: 11 | I9: 11 | J9: =H9-I9 -> 0 | K9: 10 | L9: 9 | M9: =K9-L9 -> 1
A10: PRETA | B10: 9 | C10: 5 | D10: =B10-C10 -> 4 | E10: 15 | F10: 10 | G10: =E10-F10 -> 5 | H10: 6 | I10: 4 | J10: =H10-I10 -> 2 | K10: 6 | L10: 5 | M10: =K10-L10 -> 1
A11: AZUL | B11: 11 | C11: 11 | D11: =B11-C11 -> 0 | E11: 17 | F11: 17 | G11: =E11-F11 -> 0 | H11: 13 | I11: 13 | J11: =H11-I11 -> 0 | K11: 10 | L11: 9 | M11: =K11-L11 -> 1
A13: Masculina | B13: P | D13: Atual | E13: M | G13: Atual | H13: G | J13: Atual | K13: GG | M13: Atual
A14: VERMELHA | B14: 8 | C14: 8 | D14: =B14-C14 -> 0 | E14: 11 | F14: 10 | G14: =E14-F14 -> 1 | H14: 14 | I14: 13 | J14: =H14-I14 -> 1 | K14: 13 | L14: 12 | M14: =K14-L14 -> 1
A15: BRANCA | B15: 4 | C15: 4 | D15: =B15-C15 -> 0 | E15: 11 | F15: 11 | G15: =E15-F15 -> 0 | H15: 2 | I15: 2 | J15: =H15-I15 -> 0 | K15: 3 | L15: 2 | M15: =K15-L15 -> 1
A16: VERDE | B16: 7 | C16: 7 | D16: =B16-C16 -> 0 | E16: 10 | F16: 9 | G16: =E16-F16 -> 1 | H16: 16 | I16: 14 | J16: =H16-I16 -> 2 | K16: 13 | L16: 13 | M16: =K16-L16 -> 0
A17: PRETA | B17: 3 | C17: 1 | D17: =B17-C17 -> 2 | E17: 8 | F17: 0 | G17: =E17-F17 -> 8 | H17: 10 | I17: 6 | J17: =H17-I17 -> 4 | K17: 5 | L17: 2 | M17: =K17-L17 -> 3
A18: AZUL | B18: 8 | C18: 8 | D18: =B18-C18 -> 0 | E18: 12 | F18: 12 | G18: =E18-F18 -> 0 | H18: 17 | I18: 17 | J18: =H18-I18 -> 0 | K18: 13 | L18: 13 | M18: =K18-L18 -> 0

Sheet Lista preços
A1: Id | B1: Produto | C1: Código (SKU) | D1: Preço | E1: Custo | F1: Preço Promocional
A2: 888001812 | B2: 0015 - FOLHA SECA - FLORAL | C2: 0015FSFLORAL | D2: 279.9 | E2: 170 | F2: =ROUNDUP(((($E2*'Calculadora de preço'!$B$4)+($E2*#REF!))*100)/(100-'Calculadora de preço'!$B$5), -1) -> #REF! | G2: 1
A3: 825885774 | B3: 0015 - FOLHA SECA - FLORAL - 36 | C3: 0015FOLHA36 | D3: 279.9 | E3: 170 | F3: =ROUNDUP(((($E3*'Calculadora de preço'!$B$4)+($E3*#REF!))*100)/(100-'Calculadora de preço'!$B$5), -1) -> #REF!
A4: 888001960 | B4: 0015 - FOLHA SECA - FLORAL - 38 | C4: 0015FOLHA38 | D4: 279.9 | E4: 170 | F4: =ROUNDUP(((($E4*'Calculadora de preço'!$B$4)+($E4*#REF!))*100)/(100-'Calculadora de preço'!$B$5), -1) -> #REF!
A5: 888001963 | B5: 0015 - FOLHA SECA - FLORAL - 42 | C5: 0015FOLHA42 | D5: 279.9 | E5: 170 | F5: =ROUNDUP(((($E5*'Calculadora de preço'!$B$4)+($E5*#REF!))*100)/(100-'Calculadora de preço'!$B$5), -1) -> #REF!
A6: 888001966 | B6: 0015 - FOLHA SECA - FLORAL - 44 | C6: 0015FOLHA44 | D6: 279.9 | E6: 170 | F6: =ROUNDUP(((($E6*'Calculadora de preço'!$B$4)+($E6*#REF!))*100)/(100-'Calculadora de preço'!$B$5), -1) -> #REF!
A7: 888001969 | B7: 0015 - FOLHA SECA - FLORAL - 45 | C7: 0015FOLHA45 | D7: 279.9 | E7: 170 | F7: =ROUNDUP(((($E7*'Calculadora de preço'!$B$4)+($E7*#REF!))*100)/(100-'Calculadora de preço'!$B$5), -1) -> #REF!
A8: 888002599 | B8: 0015 - MADEIRA SECA - FLORAL PINK | C8: 0015MADSECAFLORPINK | D8: 209.9 | E8: 123 | F8: =ROUNDUP(((($E8*'Calculadora de preço'!$B$4)+($E8*#REF!))*100)/(100-'Calculadora de preço'!$B$5), -1) -> #REF! | G8: 1
A9: 825885771 | B9: 0015 - MADEIRA SECA - FLORAL PINK - 34 | C9: 0015PINK34 | D9: 209.9 | E9: 123 | F9: =ROUNDUP(((($E9*'Calculadora de preço'!$B$4)+($E9*#REF!))*100)/(100-'Calculadora de preço'!$B$5), -1) -> #REF!
A10: 888002803 | B10: 0015 - MADEIRA SECA - FLORAL PINK - 35 | C10: 0015PINK35 | D10: 209.9 | E10: 123 | F10: =ROUNDUP(((($E10*'Calculadora de preço'!$B$4)+($E10*#REF!))*100)/(100-'Calculadora de preço'!$B$5), -1) -> #REF!
A11: 888002806 | B11: 0015 - MADEIRA SECA - FLORAL PINK - 37 | C11: 0015PINK37 | D11: 209.9 | E11: 123 | F11: =ROUNDUP(((($E11*'Calculadora de preço'!$B$4)+($E11*#REF!))*100)/(100-'Calculadora de preço'!$B$5), -1) -> #REF!
A12: 888002809 | B12: 0015 - MADEIRA SECA - FLORAL PINK - 38 | C12: 0015PINK38 | D12: 209.9 | E12: 123 | F12: =ROUNDUP(((($E12*'Calculadora de preço'!$B$4)+($E12*#REF!))*100)/(100-'Calculadora de preço'!$B$5), -1) -> #REF!
A13: 888004101 | B13: 0015 - NOBUK CAFÉ - FLORAL | C13: 0015NCFLORAL | D13: 279.9 | E13: 170 | F13: =ROUNDUP(((($E13*'Calculadora de preço'!$B$4)+($E13*#REF!))*100)/(100-'Calculadora de preço'!$B$5), -1) -> #REF! | G13: 1
A14: 825885777 | B14: 0015 - NOBUK CAFÉ - FLORAL - 39 | C14: 0015NCFLORAL39 | D14: 279.9 | E14: 170 | F14: =ROUNDUP(((($E14*'Calculadora de preço'!$B$4)+($E14*#REF!))*100)/(100-'Calculadora de preço'!$B$5), -1) -> #REF!
A15: 888004148 | B15: 0015 - NOBUK CAFÉ - FLORAL - 41 | C15: 0015NCFLORAL41 | D15: 279.9 | E15: 170 | F15: =ROUNDUP(((($E15*'Calculadora de preço'!$B$4)+($E15*#REF!))*100)/(100-'Calculadora de preço'!$B$5), -1) -> #REF!
A16: 888004151 | B16: 0015 - NOBUK CAFÉ - FLORAL - 42 | C16: 0015NCFLORAL42 | D16: 279.9 | E16: 170 | F16: =ROUNDUP(((($E16*'Calculadora de preço'!$B$4)+($E16*#REF!))*100)/(100-'Calculadora de preço'!$B$5), -1) -> #REF!
A17: 888004154 | B17: 0015 - NOBUK CAFÉ - FLORAL - 43 | C17: 0015NCFLORAL43 | D17: 279.9 | E17: 170 | F17: =ROUNDUP(((($E17*'Calculadora de preço'!$B$4)+($E17*#REF!))*100)/(100-'Calculadora de preço'!$B$5), -1) -> #REF!
A18: 888004216 | B18: 015QL - BOTINA LAT.CAFE SOLA TROV | C18: 015QLST | D18: 199.9 | E18: 97.28 | F18: =ROUNDUP(((($E18*'Calculadora de preço'!$B$4)+($E18*#REF!))*100)/(100-'Calculadora de preço'!$B$5), -1) -> #REF! | G18: 1
A19: 888004817 | B19: 015QL - BOTINA LAT.CAFE SOLA TROV - 21 | C19: 015QLST-1 | D19: 199.9 | E19: 97.28 | F19: =ROUNDUP(((($E19*'Calculadora de preço'!$B$4)+($E19*#REF!))*100)/(100-'Calculadora de preço'!$B$5), -1) -> #REF!
A20: 888004822 | B20: 015QL - BOTINA LAT.CAFE SOLA TROV - 25 | C20: 015QLST-2 | D20: 199.9 | E20: 97.28 | F20: =ROUNDUP(((($E20*'Calculadora de preço'!$B$4)+($E20*#REF!))*100)/(100-'Calculadora de preço'!$B$5), -1) -> #REF!
A21: 888004825 | B21: 015QL - BOTINA LAT.CAFE SOLA TROV - 26 | C21: 015QLST-3 | D21: 199.9 | E21: 97.28 | F21: =ROUNDUP(((($E21*'Calculadora de preço'!$B$4)+($E21*#REF!))*100)/(100-'Calculadora de preço'!$B$5), -1) -> #REF!
A22: 888004828 | B22: 015QL - BOTINA LAT.CAFE SOLA TROV - 27 | C22: 015QLST-4 | D22: 199.9 | E22: 97.28 | F22: =ROUNDUP(((($E22*'Calculadora de preço'!$B$4)+($E22*#REF!))*100)/(100-'Calculadora de preço'!$B$5), -1) -> #REF!
A23: 888004831 | B23: 015QL - BOTINA LAT.CAFE SOLA TROV - 28 | C23: 015QLST-5 | D23: 199.9 | E23: 97.28 | F23: =ROUNDUP(((($E23*'Calculadora de preço'!$B$4)+($E23*#REF!))*100)/(100-'Calculadora de preço'!$B$5), -1) -> #REF!
A24: 888004834 | B24: 015QL - BOTINA LAT.CAFE SOLA TROV - 29 | C24: 015QLST-6 | D24: 199.9 | E24: 97.28 | F24: =ROUNDUP(((($E24*'Calculadora de preço'!$B$4)+($E24*#REF!))*100)/(100-'Calculadora de preço'!$B$5), -1) -> #REF!
A25: 888004837 | B25: 015QL - BOTINA LAT.CAFE SOLA TROV - 30 | C25: 015QLST-7 | D25: 199.9 | E25: 97.28 | F25: =ROUNDUP(((($E25*'Calculadora de preço'!$B$4)+($E25*#REF!))*100)/(100-'Calculadora de preço'!$B$5), -1) -> #REF!
A26: 888004840 | B26: 015QL - BOTINA LAT.CAFE SOLA TROV - 31 | C26: 015QLST-8 | D26: 199.9 | E26: 97.28 | F26: =ROUNDUP(((($E26*'Calculadora de preço'!$B$4)+($E26*#REF!))*100)/(100-'Calculadora de preço'!$B$5), -1) -> #REF!
A27: 888004814 | B27: 015QL - BOTINA LAT.CAFE SOLA TROV - 34 | C27: 015QLST-9 | D27: 199.9 | E27: 97.28 | F27: =ROUNDUP(((($E27*'Calculadora de preço'!$B$4)+($E27*#REF!))*100)/(100-'Calculadora de preço'!$B$5), -1) -> #REF!
A28: 888006948 | B28: 1000 FLOOTER PRETO | C28: 1000FP | D28: 449.9 | E28: 275 | F28: =ROUNDUP(((($E28*'Calculadora de preço'!$B$4)+($E28*#REF!))*100)/(100-'Calculadora de preço'!$B$5), -1) -> #REF! | G28: 1
A29: 888008149 | B29: 1000 FLOOTER PRETO - 34 | C29: 1000FP-1 | D29: 449.9 | E29: 275 | F29: =ROUNDUP(((($E29*'Calculadora de preço'!$B$4)+($E29*#REF!))*100)/(100-'Calculadora de preço'!$B$5), -1) -> #REF!
A30: 888008152 | B30: 1000 FLOOTER PRETO - 36 | C30: 1000FP-2 | D30: 449.9 | E30: 275 | F30: =ROUNDUP(((($E30*'Calculadora de preço'!$B$4)+($E30*#REF!))*100)/(100-'Calculadora de preço'!$B$5), -1) -> #REF!
A31: 888008155 | B31: 1000 FLOOTER PRETO - 38 | C31: 1000FP-3 | D31: 449.9 | E31: 275 | F31: =ROUNDUP(((($E31*'Calculadora de preço'!$B$4)+($E31*#REF!))*100)/(100-'Calculadora de preço'!$B$5), -1) -> #REF!
A32: 888008146 | B32: 1000 FLOOTER PRETO - 40 | C32: 1000FP-4 | D32: 449.9 | E32: 275 | F32: =ROUNDUP(((($E32*'Calculadora de preço'!$B$4)+($E32*#REF!))*100)/(100-'Calculadora de preço'!$B$5), -1) -> #REF!
A33: 888026648 | B33: 1000 MADEIRA SECA CRAZY | C33: 1000MSCRAZY | D33: 479.9 | E33: 290 | F33: =ROUNDUP(((($E33*'Calculadora de preço'!$B$4)+($E33*#REF!))*100)/(100-'Calculadora de preço'!$B$5), -1) -> #REF! | G33: 1
A34: 825885789 | B34: 1000 MADEIRA SECA CRAZY - 37 | C34: 1000MSCRAZY-1 | D34: 479.9 | E34: 290 | F34: =ROUNDUP(((($E34*'Calculadora de preço'!$B$4)+($E34*#REF!))*100)/(100-'Calculadora de preço'!$B$5), -1) -> #REF!
A35: 888026675 | B35: 1000 MADEIRA SECA CRAZY - 39 | C35: 1000MSCRAZY-2 | D35: 479.9 | E35: 290 | F35: =ROUNDUP(((($E35*'Calculadora de preço'!$B$4)+($E35*#REF!))*100)/(100-'Calculadora de preço'!$B$5), -1) -> #REF!
A36: 888026678 | B36: 1000 MADEIRA SECA CRAZY - 41 | C36: 1000MSCRAZY-3 | D36: 479.9 | E36: 290 | F36: =ROUNDUP(((($E36*'Calculadora de preço'!$B$4)+($E36*#REF!))*100)/(100-'Calculadora de preço'!$B$5), -1) -> #REF!
A37: 888026681 | B37: 1000 MADEIRA SECA CRAZY - 43 | C37: 1000MSCRAZY-4 | D37: 479.9 | E37: 290 | F37: =ROUNDUP(((($E37*'Calculadora de preço'!$B$4)+($E37*#REF!))*100)/(100-'Calculadora de preço'!$B$5), -1) -> #REF!
A38: 888026759 | B38: 1002 CASCA DE ARVORE | C38: 1002CDA | D38: 479.9 | E38: 290 | F38: =ROUNDUP(((($E38*'Calculadora de preço'!$B$4)+($E38*#REF!))*100)/(100-'Calculadora de preço'!$B$5), -1) -> #REF! | G38: 1
A39: 825885786 | B39: 1002 CASCA DE ARVORE - 36 | C39: 10021002CDA-1 | D39: 479.9 | E39: 290 | F39: =ROUNDUP(((($E39*'Calculadora de preço'!$B$4)+($E39*#REF!))*100)/(100-'Calculadora de preço'!$B$5), -1) -> #REF!
A40: 888026769 | B40: 1002 CASCA DE ARVORE - 38 | C40: 1002CDA-2 | D40: 479.9 | E40: 290 | F40: =ROUNDUP(((($E40*'Calculadora de preço'!$B$4)+($E40*#REF!))*100)/(100-'Calculadora de preço'!$B$5), -1) -> #REF!
A41: 888026772 | B41: 1002 CASCA DE ARVORE - 40 | C41: 1002CDA-3 | D41: 479.9 | E41: 290 | F41: =ROUNDUP(((($E41*'Calculadora de preço'!$B$4)+($E41*#REF!))*100)/(100-'Calculadora de preço'!$B$5), -1) -> #REF!
A42: 888026775 | B42: 1002 CASCA DE ARVORE - 42 | C42: 1002CDA-4 | D42: 479.9 | E42: 290 | F42: =ROUNDUP(((($E42*'Calculadora de preço'!$B$4)+($E42*#REF!))*100)/(100-'Calculadora de preço'!$B$5), -1) -> #REF!
A43: 888026859 | B43: 1100 NOBUK FENDY FLORES DO CAMPO | C43: 1100NFFDC | D43: 449.9 | E43: 275 | F43: =ROUNDUP(((($E43*'Calculadora de preço'!$B$4)+($E43*#REF!))*100)/(100-'Calculadora de preço'!$B$5), -1) -> #REF! | G43: 1
A44: 825885780 | B44: 1100 NOBUK FENDY FLORES DO CAMPO - 33 | C44: 1100NFFDC-1 | D44: 449.9 | E44: 275 | F44: =ROUNDUP(((($E44*'Calculadora de preço'!$B$4)+($E44*#REF!))*100)/(100-'Calculadora de preço'!$B$5), -1) -> #REF!
A45: 888026936 | B45: 1100 NOBUK FENDY FLORES DO CAMPO - 35 | C45: 1100NFFDC-2 | D45: 449.9 | E45: 275 | F45: =ROUNDUP(((($E45*'Calculadora de preço'!$B$4)+($E45*#REF!))*100)/(100-'Calculadora de preço'!$B$5), -1) -> #REF!
A46: 888026939 | B46: 1100 NOBUK FENDY FLORES DO CAMPO - 37 | C46: 1100NFFDC-3 | D46: 449.9 | E46: 275 | F46: =ROUNDUP(((($E46*'Calculadora de preço'!$B$4)+($E46*#REF!))*100)/(100-'Calculadora de preço'!$B$5), -1) -> #REF!
A47: 888026942 | B47: 1100 NOBUK FENDY FLORES DO CAMPO - 39 | C47: 1100NFFDC-4 | D47: 449.9 | E47: 275 | F47: =ROUNDUP(((($E47*'Calculadora de preço'!$B$4)+($E47*#REF!))*100)/(100-'Calculadora de preço'!$B$5), -1) -> #REF!
A48: 888027072 | B48: 1250 - FLORAL PINK - MADEIRA SECA | C48: 1250FPMS | D48: 359.9 | E48: 219 | F48: =ROUNDUP(((($E48*'Calculadora de preço'!$B$4)+($E48*#REF!))*100)/(100-'Calculadora de preço'!$B$5), -1) -> #REF! | G48: 1
A49: 825885768 | B49: 1250 - FLORAL PINK - MADEIRA SECA - 34 | C49: 1250FPMS-1 | D49: 359.9 | E49: 219 | F49: =ROUNDUP(((($E49*'Calculadora de preço'!$B$4)+($E49*#REF!))*100)/(100-'Calculadora de preço'!$B$5), -1) -> #REF!
A50: 888027164 | B50: 1250 - FLORAL PINK - MADEIRA SECA - 35 | C50: 1250FPMS-2 | D50: 359.9 | E50: 219 | F50: =ROUNDUP(((($E50*'Calculadora de preço'!$B$4)+($E50*#REF!))*100)/(100-'Calculadora de preço'!$B$5), -1) -> #REF!
A51: 888027167 | B51: 1250 - FLORAL PINK - MADEIRA SECA - 36 | C51: 1250FPMS-3 | D51: 359.9 | E51: 219 | F51: =ROUNDUP(((($E51*'Calculadora de preço'!$B$4)+($E51*#REF!))*100)/(100-'Calculadora de preço'!$B$5), -1) -> #REF!
A52: 888027170 | B52: 1250 - FLORAL PINK - MADEIRA SECA - 37 | C52: 1250FPMS-4 | D52: 359.9 | E52: 219 | F52: =ROUNDUP(((($E52*'Calculadora de preço'!$B$4)+($E52*#REF!))*100)/(100-'Calculadora de preço'!$B$5), -1) -> #REF!
A53: 888027173 | B53: 1250 - FLORAL PINK - MADEIRA SECA - 38 | C53: 1250FPMS-5 | D53: 359.9 | E53: 219 | F53: =ROUNDUP(((($E53*'Calculadora de preço'!$B$4)+($E53*#REF!))*100)/(100-'Calculadora de preço'!$B$5), -1) -> #REF!
A54: 821620743 | B54: Abridor de Garrafas - Sacudidos | D54: 29.9 | E54: 11.51 | F54: =ROUNDUP(((($E54*'Calculadora de preço'!$B$4)+($E54*#REF!))*100)/(100-'Calculadora de preço'!$B$5), -1) -> #REF!
A55: 813754503 | B55: ADESIVO DE CHAPEU SACUDIDOS - AGRO NAO PARA - PRETO E LARANJA | D55: 14.9 | E55: 5.5 | F55: =ROUNDUP(((($E55*'Calculadora de preço'!$B$4)+($E55*#REF!))*100)/(100-'Calculadora de preço'!$B$5), -1) -> #REF!
A56: 813754358 | B56: ADESIVO DE CHAPEU SACUDIDOS - ETIQUETA SACUDIDOS | D56: 14.9 | E56: 5.5 | F56: =ROUNDUP(((($E56*'Calculadora de preço'!$B$4)+($E56*#REF!))*100)/(100-'Calculadora de preço'!$B$5), -1) -> #REF!
A57: 813754447 | B57: ADESIVO DE CHAPEU SACUDIDOS - LOGO ESTILIZADO - BRANCO | D57: 14.9 | E57: 5.5 | F57: =ROUNDUP(((($E57*'Calculadora de preço'!$B$4)+($E57*#REF!))*100)/(100-'Calculadora de preço'!$B$5), -1) -> #REF!
A58: 813754456 | B58: ADESIVO DE CHAPEU SACUDIDOS - LOGO ESTILIZADO - DOURADO | D58: 14.9 | E58: 5.5 | F58: =ROUNDUP(((($E58*'Calculadora de preço'!$B$4)+($E58*#REF!))*100)/(100-'Calculadora de preço'!$B$5), -1) -> #REF!
A59: 813754364 | B59: ADESIVO DE CHAPEU SACUDIDOS - LOGO ROSA | D59: 14.9 | E59: 5.5 | F59: =ROUNDUP(((($E59*'Calculadora de preço'!$B$4)+($E59*#REF!))*100)/(100-'Calculadora de preço'!$B$5), -1) -> #REF!
A60: 813754493 | B60: ADESIVO DE CHAPEU SACUDIDOS - LOGO SACUDIDOS | D60: 14.9 | E60: 5.5 | F60: =ROUNDUP(((($E60*'Calculadora de preço'!$B$4)+($E60*#REF!))*100)/(100-'Calculadora de preço'!$B$5), -1) -> #REF!
A61: 813754373 | B61: ADESIVO DE CHAPEU SACUDIDOS - MEDALHA SAO BENTO | D61: 14.9 | E61: 5.5 | F61: =ROUNDUP(((($E61*'Calculadora de preço'!$B$4)+($E61*#REF!))*100)/(100-'Calculadora de preço'!$B$5), -1) -> #REF!
A62: 813754370 | B62: ADESIVO DE CHAPEU SACUDIDOS - PENA - VERDE E AMARELO | D62: 14.9 | E62: 5.5 | F62: =ROUNDUP(((($E62*'Calculadora de preço'!$B$4)+($E62*#REF!))*100)/(100-'Calculadora de preço'!$B$5), -1) -> #REF!
A63: 796092376 | B63: ADESIVO MADE IN MATO PEQUENO 10,5 | D63: 14.9 | E63: 4.95 | F63: =ROUNDUP(((($E63*'Calculadora de preço'!$B$4)+($E63*#REF!))*100)/(100-'Calculadora de preço'!$B$5), -1) -> #REF!
A64: 816436708 | B64: ADESIVO SACUDIDO'S | D64: 14.9 | E64: 0 | F64: =ROUNDUP(((($E64*'Calculadora de preço'!$B$4)+($E64*#REF!))*100)/(100-'Calculadora de preço'!$B$5), -1) -> #REF!
A65: 807046395 | B65: ARREIO BANANA JC C/ARG. INOX C/TRAVESSAO.... | D65: 499.9 | E65: 291.45 | F65: =ROUNDUP(((($E65*'Calculadora de preço'!$B$4)+($E65*#REF!))*100)/(100-'Calculadora de preço'!$B$5), -1) -> #REF! | G65: 1
A66: 810056870 | B66: BABYLOOK TEXAS FARM - CF129 - DO PP AO GG - ROXO AMORA | D66: 119.9 | E66: 48.9 | F66: =ROUNDUP(((($E66*'Calculadora de preço'!$B$4)+($E66*#REF!))*100)/(100-'Calculadora de preço'!$B$5), -1) -> #REF! | G66: 1
A67: 810056851 | B67: BABYLOOK TEXAS FARM - CF238 - DO PP AO GG - ROXO AMORA | D67: 119.9 | E67: 48.9 | F67: =ROUNDUP(((($E67*'Calculadora de preço'!$B$4)+($E67*#REF!))*100)/(100-'Calculadora de preço'!$B$5), -1) -> #REF!
A68: 810056797 | B68: BABYLOOK TEXAS FARM - CF268 - DO PP AO GG - PRETO | D68: 119.9 | E68: 48.9 | F68: =ROUNDUP(((($E68*'Calculadora de preço'!$B$4)+($E68*#REF!))*100)/(100-'Calculadora de preço'!$B$5), -1) -> #REF!
A69: 816032859 | B69: BAINHA CELULAR GG PASSADOR C FORRO | D69: 95.9 | E69: 39.9 | F69: =ROUNDUP(((($E69*'Calculadora de preço'!$B$4)+($E69*#REF!))*100)/(100-'Calculadora de preço'!$B$5), -1) -> #REF! | G69: 1
A70: 807046398 | B70: BAINHA DE COURO P/CANIVETE....................... | D70: 29.99 | E70: 10.34 | F70: =ROUNDUP(((($E70*'Calculadora de preço'!$B$4)+($E70*#REF!))*100)/(100-'Calculadora de preço'!$B$5), -1) -> #REF! | G70: 1
A71: 803544054 | B71: BANDANA PROTECAO UV - UNICO | D71: 59.9 | E71: 27.64 | F71: =ROUNDUP(((($E71*'Calculadora de preço'!$B$4)+($E71*#REF!))*100)/(100-'Calculadora de preço'!$B$5), -1) -> #REF!
A72: 810056779 | B72: BANDANA TEXAS FARM | WAY TO LIVE - BN014 - PRETO | D72: 65.9 | E72: 26.9 | F72: =ROUNDUP(((($E72*'Calculadora de preço'!$B$4)+($E72*#REF!))*100)/(100-'Calculadora de preço'!$B$5), -1) -> #REF!
A73: 806785802 | B73: BANDINHA B004 | D73: 85 | E73: 35 | F73: =ROUNDUP(((($E73*'Calculadora de preço'!$B$4)+($E73*#REF!))*100)/(100-'Calculadora de preço'!$B$5), -1) -> #REF!
A74: 806785806 | B74: BANDINHA COM APLIQUE | D74: 75 | E74: 30 | F74: =ROUNDUP(((($E74*'Calculadora de preço'!$B$4)+($E74*#REF!))*100)/(100-'Calculadora de preço'!$B$5), -1) -> #REF!
A75: 827101770 | B75: BARBICACHO | D75: 49.9 | E75: 20 | F75: =ROUNDUP(((($E75*'Calculadora de preço'!$B$4)+($E75*#REF!))*100)/(100-'Calculadora de preço'!$B$5), -1) -> #REF!
A76: 888004591 | B76: BASICA F PROTECAO UV | C76: BASFPROTUV | D76: 179.9 | E76: 81.75 | F76: =ROUNDUP(((($E76*'Calculadora de preço'!$B$4)+($E76*#REF!))*100)/(100-'Calculadora de preço'!$B$5), -1) -> #REF!
A77: 803544031 | B77: BASICA F PROTECAO UV - G | C77: BASFPROTUV-G | D77: 179.9 | E77: 81.75 | F77: =ROUNDUP(((($E77*'Calculadora de preço'!$B$4)+($E77*#REF!))*100)/(100-'Calculadora de preço'!$B$5), -1) -> #REF!
A78: 803544034 | B78: BASICA F PROTECAO UV - GG | C78: BASFPROTUV-GG | D78: 179.9 | E78: 81.75 | F78: =ROUNDUP(((($E78*'Calculadora de preço'!$B$4)+($E78*#REF!))*100)/(100-'Calculadora de preço'!$B$5), -1) -> #REF!
A79: 803544028 | B79: BASICA F PROTECAO UV - M | C79: BASFPROTUV-M | D79: 179.9 | E79: 81.75 | F79: =ROUNDUP(((($E79*'Calculadora de preço'!$B$4)+($E79*#REF!))*100)/(100-'Calculadora de preço'!$B$5), -1) -> #REF!
A80: 803544025 | B80: BASICA F PROTECAO UV - P | C80: BASFPROTUV-P | D80: 179.9 | E80: 81.75 | F80: =ROUNDUP(((($E80*'Calculadora de preço'!$B$4)+($E80*#REF!))*100)/(100-'Calculadora de preço'!$B$5), -1) -> #REF!
A81: 888005061 | B81: BASICA M PROTECAO UV | C81: BASMPROTUV | D81: 189.9 | E81: 92.65 | F81: =ROUNDUP(((($E81*'Calculadora de preço'!$B$4)+($E81*#REF!))*100)/(100-'Calculadora de preço'!$B$5), -1) -> #REF!
A82: 803544043 | B82: BASICA M PROTECAO UV - G | C82: BASMPROTUV-G | D82: 189.9 | E82: 92.65 | F82: =ROUNDUP(((($E82*'Calculadora de preço'!$B$4)+($E82*#REF!))*100)/(100-'Calculadora de preço'!$B$5), -1) -> #REF!
A83: 803544051 | B83: BASICA M PROTECAO UV - G1 | C83: BASMPROTUV-G1 | D83: 189.9 | E83: 92.65 | F83: =ROUNDUP(((($E83*'Calculadora de preço'!$B$4)+($E83*#REF!))*100)/(100-'Calculadora de preço'!$B$5), -1) -> #REF!
A84: 803544048 | B84: BASICA M PROTECAO UV - GG | C84: BASMPROTUV-GG | D84: 189.9 | E84: 92.65 | F84: =ROUNDUP(((($E84*'Calculadora de preço'!$B$4)+($E84*#REF!))*100)/(100-'Calculadora de preço'!$B$5), -1) -> #REF!
A85: 803544040 | B85: BASICA M PROTECAO UV - M | C85: BASMPROTUV-M | D85: 189.9 | E85: 92.65 | F85: =ROUNDUP(((($E85*'Calculadora de preço'!$B$4)+($E85*#REF!))*100)/(100-'Calculadora de preço'!$B$5), -1) -> #REF!
A86: 803544037 | B86: BASICA M PROTECAO UV - P | C86: BASMPROTUV-P | D86: 189.9 | E86: 92.65 | F86: =ROUNDUP(((($E86*'Calculadora de preço'!$B$4)+($E86*#REF!))*100)/(100-'Calculadora de preço'!$B$5), -1) -> #REF!
A87: 888005017 | B87: Blusa Cowgirl Boots | C87: BLUCOWBO | D87: 109.9 | E87: 46 | F87: =ROUNDUP(((($E87*'Calculadora de preço'!$B$4)+($E87*#REF!))*100)/(100-'Calculadora de preço'!$B$5), -1) -> #REF! | G87: 1
A88: 804464698 | B88: Blusa Cowgirl Boots - G | C88: BLUCOWBO-G | D88: 109.9 | E88: 46 | F88: =ROUNDUP(((($E88*'Calculadora de preço'!$B$4)+($E88*#REF!))*100)/(100-'Calculadora de preço'!$B$5), -1) -> #REF!
A89: 804464701 | B89: Blusa Cowgirl Boots - M | C89: BLUCOWBO-M | D89: 109.9 | E89: 46 | F89: =ROUNDUP(((($E89*'Calculadora de preço'!$B$4)+($E89*#REF!))*100)/(100-'Calculadora de preço'!$B$5), -1) -> #REF!
A90: 804464706 | B90: Blusa Cowgirl Boots - P | C90: BLUCOWBO-P | D90: 109.9 | E90: 46 | F90: =ROUNDUP(((($E90*'Calculadora de preço'!$B$4)+($E90*#REF!))*100)/(100-'Calculadora de preço'!$B$5), -1) -> #REF!
A91: 804464709 | B91: Blusa Cowgirl Boots - PP | C91: BLUCOWBO-PP | D91: 109.9 | E91: 46 | F91: =ROUNDUP(((($E91*'Calculadora de preço'!$B$4)+($E91*#REF!))*100)/(100-'Calculadora de preço'!$B$5), -1) -> #REF!
A92: 815454541 | B92: BLUSA MEIO ZIPER - SUL DE MINAS | D92: 169.9 | E92: 79 | F92: =ROUNDUP(((($E92*'Calculadora de preço'!$B$4)+($E92*#REF!))*100)/(100-'Calculadora de preço'!$B$5), -1) -> #REF! | G92: 1
A93: 888005075 | B93: Blusa Saddle Up Cowboy | C93: BLUSADUPCO | D93: 109.9 | E93: 46 | F93: =ROUNDUP(((($E93*'Calculadora de preço'!$B$4)+($E93*#REF!))*100)/(100-'Calculadora de preço'!$B$5), -1) -> #REF! | G93: 1
A94: 804464732 | B94: Blusa Saddle Up Cowboy - G | C94: BLUSADUPCO-G | D94: 109.9 | E94: 46 | F94: =ROUNDUP(((($E94*'Calculadora de preço'!$B$4)+($E94*#REF!))*100)/(100-'Calculadora de preço'!$B$5), -1) -> #REF!
A95: 804464728 | B95: Blusa Saddle Up Cowboy - GG | C95: BLUSADUPCO-GG | D95: 109.9 | E95: 46 | F95: =ROUNDUP(((($E95*'Calculadora de preço'!$B$4)+($E95*#REF!))*100)/(100-'Calculadora de preço'!$B$5), -1) -> #REF!
A96: 804464735 | B96: Blusa Saddle Up Cowboy - M | C96: BLUSADUPCO-M | D96: 109.9 | E96: 46 | F96: =ROUNDUP(((($E96*'Calculadora de preço'!$B$4)+($E96*#REF!))*100)/(100-'Calculadora de preço'!$B$5), -1) -> #REF!
A97: 804464738 | B97: Blusa Saddle Up Cowboy - P | C97: BLUSADUPCO-P | D97: 109.9 | E97: 46 | F97: =ROUNDUP(((($E97*'Calculadora de preço'!$B$4)+($E97*#REF!))*100)/(100-'Calculadora de preço'!$B$5), -1) -> #REF!
A98: 888005096 | B98: Blusa Tamborzeira | C98: BLUTAMB | D98: 109.9 | E98: 46 | F98: =ROUNDUP(((($E98*'Calculadora de preço'!$B$4)+($E98*#REF!))*100)/(100-'Calculadora de preço'!$B$5), -1) -> #REF! | G98: 1
A99: 804464716 | B99: Blusa Tamborzeira - G | C99: BLUTAMB-G | D99: 109.9 | E99: 46 | F99: =ROUNDUP(((($E99*'Calculadora de preço'!$B$4)+($E99*#REF!))*100)/(100-'Calculadora de preço'!$B$5), -1) -> #REF!
A100: 804464713 | B100: Blusa Tamborzeira - GG | C100: BLUTAMB-GG | D100: 109.9 | E100: 46 | F100: =ROUNDUP(((($E100*'Calculadora de preço'!$B$4)+($E100*#REF!))*100)/(100-'Calculadora de preço'!$B$5), -1) -> #REF!
...

Sheet Página13
A1: BLUSA | B1: BLUSA MEIO ZIPER - SUL DE MINAS | C1: 169.9 | D1: 110
A2: BLUSA | B2: BLUSA ZIPER INTEIRO - SUL DE MINAS | C2: 179.9 | D2: 120
A3: BLUSA | B3: COLETE 2K JEANS | C3: 279.9 | D3: 180
A4: BLUSA | B4: CORTA VENTO | C4: 79.99 | D4: 50
A5: BLUSA | B5: JAQUETA AVIADOR 2K JEANS | C5: 359.9 | D5: 230
A6: BLUSA | B6: MOLETOM BLACK SKULL - G | C6: 219.9 | D6: 150
A7: BLUSA | B7: MOLETOM ADULTO BEM CAMPEIRO | C7: 189.9 | D7: 120
A8: BLUSA | B8: MOLETOM OLD WEST - G | C8: 219.9 | D8: 150
A9: BLUSA | B9: MOLETOM PINK COWGIRL - G | C9: 219.9 | D9: 150
A10: BLUSA | B10: MOLETON INFANTIL BEM CAMPEIRO | C10: 169.9 | D10: 90
A11: BLUSA | B11: PURA RACA JAQUETA FEM COORDENADO | C11: 159.9 | D11: 70
A12: BLUSA | B12: PURA RACA JAQUETA MASC COORDENADO | C12: 159.9 | D12: 70
... A113: BONÉ | B113: PURA RACA BONE MASC COUNTRY STYLE | C113: 99.9 | D113: 60

Sheet Página16
A1: Santander | B1: Variavel | D1: Nubank | E1: Variavel | G1: Itaú | H1: Variavel
A2: Google One | B2: 9.99 | D2: Adobe | E2: 139 | G2: Yelum | H2: 218.85 | O2: 45658 | P2: 8003.98
A3: Google F1 TV | B3: 29.9 | D3: Tim | E3: 60.99 | G3: Havan | H3: 25.6 | O3: 45689 | P3: 5869.69 | Q3: =P3+P2 -> 13873.67 | R3: pago
A4: HBO Max | B4: 44.9 | D4: Tiny | E4: 119.07 | H4: =SUM(H2:H3) -> 244.45 | O4: 45717 | P4: 4491.66 | Q4: =Q3+P4 -> 18365.33
A5: Youtube | B5: 53.9 | D5: MM | E5: 49.99 | O5: 45748 | P5: 3791.66 | Q5: =Q4+P5 -> 22156.99
A6: AWS | B6: 90.26 | D6: Neiva- Faca Motosserra | E6: 54 | O6: 45778 | P6: 3291.66 | Q6: =Q5+P6 -> 25448.65
A7: Disney | B7: 65.41 | E7: =SUM(E2:E6) -> 423.05 | O7: 45809 | P7: 2491.66 | Q7: =Q6+P7 -> 27940.31
A8: Workspace AC | B8: 98 | O8: 45839 | P8: 2491.66 | Q8: =Q7+P8 -> 30431.97
A9: Workspace SR | B9: 98 | J9: =1426.07-2.38 -> 1423.69 | O9: 45870 | P9: 2491.66 | Q9: =Q8+P9 -> 32923.63
A10: Vercel | B10: 176.2 | O10: 45901 | P10: 1791.66 | Q10: =Q9+P10 -> 34715.29
A11: IOF Vercel | B11: 6.17 | O11: 45931 | P11: 791.66 | Q11: =Q10+P11 -> 35506.95
A12: Spotify | B12: 31.9
A13: Microsoft | B13: 4 | D13: Custo Mensal | G13: A pagar
B14: =SUM(B2:B13) -> 708.63 | D14: Santander | E14: 708.63 | G14: Creditas | H14: 26135.41 | I14: pago
D15: Nubank | E15: 423.05 | G15: Emp Nu Gis | H15: 1426.07 | I15: pago
D16: Itau | E16: 244.45 | G16: Emp Nu Vi | H16: 781.72 | I16: pago | L16: 73592.86 | M16: 72 | N16: 2420.1 | O16: 2500.4 | P16: =O16-N16 -> 80.3
D17: Nubank Gis | E17: 177.81 | G17: Santander | H17: =4491.66+3791.66+3291.66+2491.66+2491.66+2491.66+1791.66+791.66 -> 21633.28 | I17: 13873.67
D18: Pura Raça | E18: 502.67 | G18: Itaú | H18: =575.6+550+550+550+250+250+250+250 -> 3225.6 | I18: 575.6
D19: Ademicon | E19: 1687 | G19: Nubank | H19: =973.07+919.07+919.07+419.07+419.07+419.07+119.07 -> 4187.49
D20: Meganet | E20: 129.9 | G20: Cresol | H20: 3744.85
D21: Sanepar | E21: 68
D22: Copel | E22: 250
E23: =SUM(E14:E22) -> 4191.51 | H23: =SUM(H14:H22) -> 61134.42
C26: 62082.12 | D26: 72 | E26: 2477.92 | F26: =E26*D26 -> 178410.24 | G26: =F26-C26 -> 116328.12
C27: 73592.86 | D27: 72 | E27: 2500.4 | F27: =D27*E27 -> 180028.8 | G27: =F27-C27 -> 106435.94 | I27: =174247.2+5781.86 -> 180029.06 | J27: =2420.1+80.3 -> 2500.4
